Workbook

Sheet Одит на цитиранията
A1: Вид дупка | B1: Абзац | C1: Източник(ци) | D1: Изречение | E1: Лист | F1: Ред | G1: Статус на реда | H1: Пакет (по източник) | I1: Решено на
A2: БЕЗ РЕД | B2: 33 | C2: [11] | D2: Консенсусната дефиниция, изведена чрез международно експертно проучване, определя електронното обучение като подход към преподаването и ученето, който | E2: — | F2: — | G2: — | H2: [11]
A3: БЕЗ РЕД | B3: 34 | C3: [11] | D3: В настоящата разработка трите понятия се разграничават така: електронното обучение е подходът към преподаването и ученето, който представя прилагания | E3: — | F3: — | G3: — | H3: [11]
A4: БЕЗ РЕД | B4: 34 | C4: [37] | D4: Clark и Mayer определят електронното обучение като обучение, доставяно чрез цифрово устройство и предназначено да подпомага ученето, като изрично отде | E4: — | F4: — | G4: — | H4: [37]
A5: БЕЗ РЕД | B5: 37 | C5: [52] | D5: Стандартът за метаданни на учебни обекти отразява това, като включва контекста на употреба сред описателните характеристики на учебния обект [52]. | E5: — | F5: — | G5: — | H5: [52]
A6: БЕЗ РЕД | B6: 40 | C6: [52] | D6: Схемата за метаданни на учебни обекти по стандарта IEEE 1484.12.1 определя структура от девет категории описателни характеристики от първо ниво, сред | E6: — | F6: — | G6: — | H6: [52]
A7: БЕЗ РЕД | B7: 42 | C7: [24] | D7: Емпиричното изследване на остарелите отговори в най-голямата платформа за програмистки въпроси установява, че над половината от тях (58,4 на сто) са б | E7: — | F7: — | G7: — | H7: [24]
A8: БЕЗ РЕД | B8: 43 | C8: [49] | D8: Ръководството на 1EdTech за съдържание, създадено с генеративен изкуствен интелект, степенува този признак в пет равнища - от съдържание, създадено от | E8: — | F8: — | G8: — | H8: [49]
A9: БЕЗ РЕД | B9: 56 | C9: [48] | D9: Експерименталното изследване на разгърнатата обратна връзка уточнява това: подробното обяснение подобрява възприемането на обратната връзка и преноса | E9: — | F9: — | G9: — | H9: [48]
A10: БЕЗ РЕД | B10: 57 | C10: [48] | D10: Разгърнатата обратна връзка се определя като допълнителна инструктивна информация към верния отговор - обяснения, насоки и стъпки за решаване [48]. | E10: — | F10: — | G10: — | H10: [48]
A11: БЕЗ РЕД | B11: 62 | C11: [46] | D11: Изследванията върху приложението на генеративния изкуствен интелект в образованието нарастват рязко след пускането на ChatGPT през ноември 2022 г.: би | E11: — | F11: — | G11: — | H11: [46]
A12: БЕЗ РЕД | B12: 63 | C12: [44] | D12: Първата е начинът на обработка на текста: моделът не работи с думи, а с по-малки единици, наречени токени, и на всяка стъпка избира следващата единица | E12: — | F12: — | G12: — | H12: [44]
A13: БЕЗ РЕД | B13: 63 | C13: [32] | D13: Емпиричните изследвания показват, че подадената информация не се използва еднакво надеждно по цялата си дължина: представянето се влошава осезаемо, ко | E13: — | F13: — | G13: — | H13: [32]
... A35: БЕЗ РЕД | B35: 221 | C35: [10, 16] | D35: Положението е свързано с документираната неравномерност на езиковото покритие в изследванията и в обучителните данни [16], [10]. | E35: — | F35: — | G35: — | H35: [10, 16]
A36: ИЗВАДКА ПОД 2 ИЗРЕЧЕНИЯ | B36: 35 | C36: [12] | D36: Значимостта на работата с дигитални ресурси за съвременния преподавател е призната и на рамково равнище: в евр | E36: Ниво 2 Твърдения | F36: 3 | G36: — | H36: [12]
A37: ИЗВАДКА ПОД 2 ИЗРЕЧЕНИЯ | B37: 44 | C37: [49] | D37: При най-високото равнище от същата скала обаче съдържанието се създава и публикува с минимален или никакъв чов | E37: Ниво 2 Твърдения | F37: 68 | G37: — | H37: [49]
A38: ИЗВАДКА ПОД 2 ИЗРЕЧЕНИЯ | B38: 55 | C38: [12] | D38: В европейската рамка DigCompEdu изборът и създаването на дигитални ресурси изрично се обвързват с отчитането н | E38: Ниво 2 Твърдения | F38: 14 | G38: — | H38: [12]
A39: ИЗВАДКА ПОД 2 ИЗРЕЧЕНИЯ | B39: 67 | C39: [27] | D39: Систематизациите на халюцинациите достигат до същия извод - надеждното им отстраняване на равнище модел остава | E39: Ниво 2 Твърдения | F39: 21 | G39: — | H39: [27]
A40: ИЗВАДКА ПОД 2 ИЗРЕЧЕНИЯ | B40: 77 | C40: [16] | D40: Първото и най-разпространено равнище е подпомогнатото създаване: преподавателят взаимодейства с инструмента чр | E40: Ниво 2 Твърдения | F40: 25 | G40: — | H40: [16]
A41: ИЗВАДКА ПОД 2 ИЗРЕЧЕНИЯ | B41: 78 | C41: [15] | D41: Рамката GAIDE предлага систематизиран процес за използване на генеративни инструменти при разработване на курс | E41: Ниво 2 Твърдения | F41: 26 | G41: — | H41: [15]
A42: ИЗВАДКА ПОД 2 ИЗРЕЧЕНИЯ | B42: 78 | C42: [14] | D42: По-широк поглед дава интегративният преглед на Chai и колектив върху 71 публикации, който картографира приложе | E42: Ниво 2 Твърдения | F42: 27 | G42: — | H42: [14]
A43: ИЗВАДКА ПОД 2 ИЗРЕЧЕНИЯ | B43: 79 | C43: [3] | D43: Показателен пример от българската практика е концептуалният дизайн на платформа за обучение по дентална анатом | E43: Ниво 2 Твърдения | F43: 28 | G43: — | H43: [3]
A44: ИЗВАДКА ПОД 2 ИЗРЕЧЕНИЯ | B44: 81 | C44: [8] | D44: Прегледът на около 130 източника за приложението на изкуствения интелект в обучението по програмиране обобщава | E44: Ниво 2 Твърдения | F44: 31 | G44: — | H44: [8]
A45: ИЗВАДКА ПОД 2 ИЗРЕЧЕНИЯ | B45: 81 | C45: [6] | D45: Публикувано описание на инструментален работен процес в българско висше училище посочва значително съкращаване | E45: Ниво 2 Твърдения | F45: 32 | G45: — | H45: [6]
A46: ИЗВАДКА ПОД 2 ИЗРЕЧЕНИЯ | B46: 82 | C46: [2] | D46: Разработена в морско висше училище система обработва над 656 000 знака учебен текст на български и английски е | E46: Ниво 2 Твърдения | F46: 33 | G46: — | H46: [2]
A47: ИЗВАДКА ПОД 2 ИЗРЕЧЕНИЯ | B47: 83 | C47: [6] | D47: Практическо ръководство за преподаватели извежда набор от правила - определяне на роля, предоставяне на контек | E47: Ниво 2 Твърдения | F47: 34 | G47: — | H47: [6]
... A86: НЕПОТВЪРДЕН СТАТУС | B86: 164 | C86: [19] | D86: Систематичният преглед на 93 изследвания в тази област показва, че още преди големите език | E86: Гл.2–3 Ниво 2 | F86: 14 | G86: Частично потвърдено | H86: [19]

Sheet Метод
B1: План за потвърждаване на цитираното от всички източници
B2: НИП „Александър Гръмов“ — Първа глава, 36 източника, 64 цитирани твърдения
B4: Защо е нужно | C4: Първа глава има 36 източника и 64 места, където конкретно твърдение е обвързано с източник. Част от записите носят признаци на риск: запис без автор с arXiv номер от 2026 г., два записа от конференции с 2026 г., един непрофилен източник (документация на Angular), един запис без DOI. Отделно 15 твърдения съдържат точни числа (проценти, брой публикации, брой стандарти), които или се потвърждават дословно, или трябва да отпаднат.
B6: Двустепенен принцип | C6: Ниво 1 проверява дали източникът съществува и дали библиографският запис е верен. Ниво 2 проверява дали конкретното твърдение наистина се съдържа в източника и на посоченото място. Източник може да мине Ниво 1 и да се провали на Ниво 2 — това е по-опасната грешка, защото не се вижда при повърхностен преглед.
B8: Ред на работа | C8: 1) Ниво 1 за всички 36 записа. 2) Ниво 2 за твърденията с приоритет „Критичен“ (числа и точни структури). 3) Ниво 2 за „Висок“. 4) Ниво 2 за останалите. 5) Отстраняване на находките в текста. 6) Финален контрол по листа „Обобщение“.
B10: Критерий „Потвърдено“ | C10: Отворен е самият източник (не абстракт, не вторично цитиране), намерено е мястото, което носи твърдението, и формулировката в текста не е по-силна от формулировката в източника. Записва се страница/раздел в колона „Намерено на“.
B12: Критерий „Частично“ | C12: Твърдението се съдържа, но обхватът, числото или категоричността се разминават. Изисква преформулиране в текста — не отпадане на източника.
B14: Специално правило: числа | C14: Всяко число се проследява до първоизточника. Ако източникът сам цитира числото от другаде (напр. ред 61), цитира се първоизточникът или се пише „по данни, цитирани в [X]“.
B16: Специално правило: локатори | C16: Локаторите [30, гл. 1/4/9/12/13/21], [27, с. 44–45], [12, обл. 2] се проверяват срещу точното издание. Номерата на глави се менят между изданията — това е най-честият източник на невярна препратка при преизползван локатор от по-старо издание.
B18: Специално правило: приписване | C18: За обобщаващи изречения („систематичните прегледи показват…“) се проверява дали изводът е на източника или е авторски синтез. Ако е авторски — цитатът се премества или се преформулира. Засегнати редове: 8, 23, 45, 46.
B20: Инструменти | C20: DOI резолвер (doi.org), Crossref, arXiv, IEEE Xplore, Google Scholar, EUR-Lex за [31], сайтовете на UNESCO, Quality Matters и IEEE SA. За българските сборници [1–6, 8, 9] — сборникът на конференцията в Русе (PDF/ISBN) или директна връзка с авторите; онлайн проверка вероятно няма да е достатъчна.
B22: Оценка на обема | C22: Ниво 1: около 3–4 часа за 36 записа. Ниво 2: около 8–12 часа, като тежестта е в 15-те критични реда и в достъпа до платените издания. Реалистичен срок при 2–3 часа дневно — 5 работни дни.
B24: Как се попълва | C24: Работи се само в колоните със светложълт фон: „Статус“, „Намерено на“, „Бележка/действие“, „Проверил“, „Дата“. Останалите колони са входни данни, извлечени от документа. Листът „Обобщение“ се преизчислява сам.
B28: Пилот humanize (28.08.2026) | C28: Раздел 1.5 беше пренаписан с humanizer и отхвърлен. Цитатите и числата се запазиха, но обемът се сви с 39 %, всичките 12 цитирани изречения бяха променени, седем конкретни детайла отпаднаха („трите оценъчни оси“, „от всички образователни степени“, „между отделни заявки“ и др.), периодът 2007–2018 излезе от изречението със своя цитат, описателно твърдение за литературата стана нормативно предписание с чужд цитат зад него, и се появи неподкрепена причинно-следствена връзка („генеративните инструменти наследяват този дефицит“). РЕШЕНИЕ: текстът НЕ се пренаписва. Инструментът се ползва само като детектор. Проверката тече срещу оригиналния текст.
B30: Ревизия 31.08.2026 — покритие на Ниво 1
B31: Листовете „Ниво 1 Източници“ и „Гл.2–3 Ниво 1“ използват стара номерация (42, съотв. междинен списък) и не покриваха целия текущ списък: 10 източника — [11], [22], [24], [32], [38], [44], [45], [46], [48], [49] — нямаха нито един ред за Ниво 1. Листът „Ниво 1 — всички 53“ е новият меродавен: съдържа всеки от 53-те записа по текущата номерация, статуса му и препратка към предишния ред. Старите листове се запазват само като история.
B33: Одит 01.09.2026 — определение за „готово“
B34: Скриптът proverka_citirane.py изброява всяко изречение с цитат и проверява дали има ред с ДОСЛОВНА извадка — от 01.09.2026 изискването е ПОНЕ ДВЕ ИЗРЕЧЕНИЯ в кавички, не отделни думи. При това изискване: 115 изречения с цитат, 30 покрити, 85 дупки — вж. листа „Одит на цитиранията“. Работата не е готова, докато скриптът не върне „дупки: 0“. Правилата са в Protokol_citirane.md.

Sheet Ниво 1 Източници
A1: № | B1: Нов № | C1: Източник (кратко) | D1: Тип | E1: Год. | F1: Идентификатор / локация | G1: Локален файл (extracted_md) | H1: Линк, използван при проверката | I1: Как се проверява | J1: Риск | K1: Основание за риска | L1: Брой твърдения | M1: Статус | N1: Намерено / DOI потвърден | O1: Бележка / действие | P1: Проверил | Q1: Дата
A2: 1 | B2: 1 | C2: А. Захариев — ИИ в ОНС „доктор“: дигитализация, регулация, кредитна акселерация | D2: Доклад в сборник (BG) | E2: 2026 | F2: Сб. „Дигитална трансформация на образованието“, Русе, с. 15–23 | G2: 2026_p-2.md | H2: https://www.conf-dte.bg/docs/2026/p-2.pdf | I2: Сборник на конференцията (PDF/ISBN); при липса — контакт с организатора или автора | J2: Среден | K2: Сборник от 2026 г.; онлайн наличност несигурна. Твърдение с нормативна конкретика (ред 49). | L2: =COUNTIF('Ниво 2 Твърдения'!$C$2:$C$65,"*["&A2&"]*") | M2: Потвърдено | N2: 2026_p-2.pdf, печ. стр. 15–23 | O2: Заглавие, автор (Андрей Захариев) и страници съвпадат. | P2: Claude (авт.) | Q2: 28.08.2026
A3: 2 | B3: 2 | C3: Д. Димитранов, Г. Димитров — ИИ за автоматизирано създаване на бази с тестови въпроси | D3: Доклад в сборник (BG) | E3: 2026 | F3: Същият сборник, с. 576–580 | G3: 2026_p-100.md | H3: https://www.conf-dte.bg/docs/2026/p-100.pdf | I3: Сборник; проверка на числата 656 000 знака / 553 въпроса | J3: Висок | K3: Носи три точни числа (ред 32) в доклад от 5 страници. | L3: =COUNTIF('Ниво 2 Твърдения'!$C$2:$C$65,"*["&A3&"]*") | M3: Потвърдено | N3: 2026_p-100.pdf, печ. стр. 576–580 | O3: Дилян Димитранов, Георги Димитров — съвпада. | P3: Claude (авт.) | Q3: 28.08.2026
A4: 3 | B4: 3 | C4: Е. Даскалова и кол. — платформа за обучение по дентална анатомия | D4: Доклад в сборник (BG) | E4: 2026 | F4: Същият сборник, с. 554–558 | G4: 2026_p-96.md | H4: https://www.conf-dte.bg/docs/2026/p-96.pdf | I4: Сборник; проверка на списъка от петима автори | J4: Среден | K4: Пет автора и точни страници — типично място за грешка при пренос. | L4: =COUNTIF('Ниво 2 Твърдения'!$C$2:$C$65,"*["&A4&"]*") | M4: Потвърдено | N4: 2026_p-96.pdf, печ. стр. 554–558 | O4: Петимата автори съвпадат, вкл. Весела Стефанова. | P4: Claude (авт.) | Q4: 28.08.2026
A5: 4 | B5: 4 | C5: М. Дамесова — генеративен ИИ и дигитален storytelling | D5: Доклад в сборник (BG) | E5: 2026 | F5: Същият сборник, с. 717–721 | G5: 2026_p-124.md | H5: https://www.conf-dte.bg/docs/2026/p-124.pdf | I5: Сборник | J5: Среден | K5: Достъп. | L5: =COUNTIF('Ниво 2 Твърдения'!$C$2:$C$65,"*["&A5&"]*") | M5: Потвърдено | N5: 2026_p-124.pdf, печ. стр. 717–721 | O5: Милена Дамесова — съвпада. | P5: Claude (авт.) | Q5: 28.08.2026
A6: 5 | B6: 5 | C6: М. Левунлиева — ИИ в образованието, перспективата на педагога | D6: Доклад в сборник (BG) | E6: 2026 | F6: Същият сборник, с. 605–610 | G6: 2026_p-106.md | H6: https://www.conf-dte.bg/docs/2026/p-106.pdf | I6: Сборник; проверка на извадката от 68 специалисти и на „трите оценъчни оси“ | J6: Висок | K6: Емпирично твърдение с число и методика (ред 41). | L6: =COUNTIF('Ниво 2 Твърдения'!$C$2:$C$65,"*["&A6&"]*") | M6: Потвърдено | N6: 2026_p-106.pdf, печ. стр. 605–610 | O6: Милена Левунлиева — съвпада. | P6: Claude (авт.) | Q6: 28.08.2026
A7: 6 | B7: 6 | C7: М. Маркова — ИИ за ускорено учене: практически инструменти | D7: Доклад в сборник (BG) | E7: 2026 | F7: Същият сборник, с. 541–546 | G7: 2026_p-94.md | H7: https://www.conf-dte.bg/docs/2026/p-94.pdf | I7: Сборник; проверка на диапазона 75–90 % | J7: Критичен | K7: Единственият източник за количествено твърдение, представено в текста в мн. ч. („публикувани описания“) — ред 31. | L7: =COUNTIF('Ниво 2 Твърдения'!$C$2:$C$65,"*["&A7&"]*") | M7: Потвърдено | N7: 2026_p-94.pdf, печ. стр. 541–546 | O7: Мая Маркова — записът е верен. ВНИМАНИЕ: твърдението в ред 31 на Ниво 2 не се потвърждава. | P7: Claude (авт.) | Q7: 28.08.2026
A8: 7 | B8: 7 | C8: С. Гафтанджиева, Р. Донева — Генеративен ИИ в образованието | D8: Списание (BG) | E8: 2025 | F8: doi: 10.53656/ped2025-9.04; Педагогика, т. 97, кн. 9, с. 1284–1297 | G8: generativen-...-reseniya.md | H8: https://journals.azbuki.bg/pedagogy/generativen-izkustven-intelekt-v-obrazovanieto-problemi-i-reseniya/view | I8: DOI резолвер; проверка на вторично цитираното число „една шеста“ | J8: Критичен | K8: Числото е цитирано от друг източник — трябва проследяване до първоизточника (ред 61). | L8: =COUNTIF('Ниво 2 Твърдения'!$C$2:$C$65,"*["&A8&"]*") | M8: Потвърдено | N8: печ. стр. 1284–1297; doi 10.53656/ped2025-9.04 | O8: Педагогика, т. 97, кн. 9, 2025 — съвпада. | P8: Claude (авт.) | Q8: 28.08.2026
A9: 8 | B9: 8 | C9: Ц. Василев — ИИ в обучението: студент и преподавател | D9: Доклад в сборник (BG) | E9: 2026 | F9: Същият сборник, с. 24–32 | G9: 2026_p-3.md | H9: https://www.conf-dte.bg/docs/2026/p-3.pdf | I9: Сборник; проверка дали докладът наистина прави преглед на ~130 източника | J9: Висок | K9: Обзор на 130 източника в доклад от 9 страници е необичайно — ред 30. | L9: =COUNTIF('Ниво 2 Твърдения'!$C$2:$C$65,"*["&A9&"]*") | M9: Потвърдено | N9: 2026_p-3.pdf, печ. стр. 24–32 | O9: Цветомир Василев — съвпада. | P9: Claude (авт.) | Q9: 28.08.2026
A10: 9 | B10: 9 | C10: Ц. Дуцова — аспекти на приложението на ИИ в образованието | D10: Доклад в сборник (BG) | E10: 2025 | F10: Трета конференция, Русе, с. 472–478 | G10: 2025_p-84.md | H10: https://www.conf-dte.bg/docs/2025/p-84.pdf | I10: Сборник | J10: Среден | K10: Достъп. | L10: =COUNTIF('Ниво 2 Твърдения'!$C$2:$C$65,"*["&A10&"]*") | M10: Потвърдено | N10: 2025_p-84.pdf, печ. стр. 472–478 | O10: Цветанка Дуцова, Трета конференция 2025 — съвпада. | P10: Claude (авт.) | Q10: 28.08.2026
A11: 10 | B11: 10 | C11: „Challenges and recommendations for LLMs-as-a-judge in multilingual settings…“ | D11: Препринт | E11: 2026 | F11: arXiv:2607.02235 | G11: https://arxiv.org/html/2607.02235v1 | H11: https://arxiv.org/html/2607.02235v1 | I11: arxiv.org/abs/2607.02235 — първо съществуване, после авторство | J11: Критичен | K11: Записът е без автори — единственият такъв в списъка. Носи две числа (над 650 публикации, 33 изследвания) и подпира извод в „Изводи от първа глава“ (редове 60, 64). | L11: =COUNTIF('Ниво 2 Твърдения'!$C$2:$C$65,"*["&A11&"]*") | M11: Потвърдено | N11: arXiv:2607.02235 — съществува | O11: Заглавието съвпада. Автори: A. S. Doğruöz, X. Liao, V. Blaschke, J. Prange, S. Li, D. I. Adelani и др. ДЕЙСТВИЕ: добави авторите — запис без автор е формално некоректен по IEEE. Числата 650/33 се потвърждават. || НАНЕСЕНО В НИП 28.08: добави „A. S. Doğruöz et al.“ пред заглавието. | P11: Claude (авт.) | Q11: 28.08.2026
A12: 11 | B12: 23 | C12: Angular Team — Angular versioning and releases | D12: Вендорска документация | E12: 2026 | F12: https://angular.dev/reference/releases | G12: https://angular.dev/reference/releases#release-frequency | H12: https://angular.dev/reference/releases#release-frequency | I12: Отваряне на страницата; проверка дали подкрепя общото твърдение | J12: Критичен | K12: Непрофилен източник в педагогически труд; използван за обобщение за „широко използвани софтуерни рамки“ въз основа на една рамка (ред 7). Обмисли замяна или отпадане. | L12: =COUNTIF('Ниво 2 Твърдения'!$C$2:$C$65,"*["&A12&"]*") | M12: Потвърдено | N12: angular.dev/reference/releases || ОТПАДА. Заменя се с Zhang и кол. (2019/2021), „An Empirical Study of Obsolete Answers on Stack Overflow“, IEEE Transactions on Software Engineering, 47(4), 850–862, doi 10.1109/TSE.2019.2906315. Рецензирано изследване вместо вендорска документация. | O12: Страницата съществува, но казва ЕДНА мажорна версия на 12 месеца и 24 месеца поддръжка (12 активна + 12 LTS). Виж ред 7 на Ниво 2. || НАНЕСЕНО В НИП 28.08: връзката става https://angular.dev/reference/releases#release-frequency — разделът наистина доказва една мажорна версия годишно, но само за Angular. | P12: Claude (авт.) | Q12: 28.08.2026
A13: 12 | B13: 13 | C13: C. Redecker — DigCompEdu | D13: Рамков документ (ЕС) | E13: 2017 | F13: JRC107466, Publications Office of the EU | G13: https://joint-research-centre.ec.europa.eu/digcompedu_en | H13: https://joint-research-centre.ec.europa.eu/digcompedu_en | I13: Свободно достъпен PDF на JRC | J13: Нисък | K13: Стабилен източник; проверява се само номерацията на област 2. | L13: =COUNTIF('Ниво 2 Твърдения'!$C$2:$C$65,"*["&A13&"]*") | M13: Потвърдено | N13: JRC107466, Publications Office of the EU, 2017 | O13: Redecker, ред. Punie — съвпада. | P13: Claude (авт.) | Q13: 28.08.2026
... A21: 20 | B21: 22 | C21: H. Yao et al. — Instructional Agents | D21: Конференция | E21: 2026 | F21: Proc. EACL 2026, т. 1, с. 4087–4109 | G21: https://aclanthology.org/2026.eacl-long.191/ | H21: https://aclanthology.org/2026.eacl-long.191/ | I21: ACL Anthology | J21: Висок | K21: Публикация от 2026 г. с точни страници — потвърди, че томът е излязъл и че страниците съвпадат. | L21: =COUNTIF('Ниво 2 Твърдения'!$C$2:$C$65,"*["&A21&"]*") | M21: Потвърдено | N21: aclanthology.org/2026.eacl-long.191, т. 1, с. 4087–4109 | O21: Съществува. Автори H. Yao, W. Xu, J. Turnau, N. Kellam, H. Wei; страниците съвпадат. DOI: 10.18653/v1/2026.eacl-long.191 — ДЕЙСТВИЕ: добави го. || НАНЕСЕНО В НИП 28.08: добави doi: 10.18653/v1/2026.eacl-long.191. | P21: Claude (авт.) | Q21: 28.08.2026
A22: 21 | B22: ОТПАДА | C22: I. du Preez, L. Jacobs — принципи за онлайн учебни материали | D22: Списание | E22: 2025 | F22: doi: 10.1080/10494820.2025.2523390 | G22: https://api.openalex.org/works/doi:10.1080/10494820.2025.2523390 | H22: https://api.openalex.org/works/doi:10.1080/10494820.2025.2523390 | I22: DOI | J22: Среден | K22: Записът е без том и книжка, само страници — непълен по IEEE. | L22: =COUNTIF('Ниво 2 Твърдения'!$C$2:$C$65,"*["&A22&"]*") | M22: Потвърдено | N22: Interactive Learning Environments, т. 34, кн. 3, с. 1435–1451, 2025 || НЯМА ДОСТЪП. ПРЕПОРЪКА: отпада. Ред 15 се пренасочва към [29] Quality Matters, който вече е потвърден (8 общи и 44 конкретни стандарта) и е точно „проверими насоки за дизайн и оценяване“. Ред 54 остава на Mayer 2021. | O22: ДЕЙСТВИЕ: добави том и книжка — записът беше непълен. || НАНЕСЕНО В НИП 28.08: добави vol. 34, no. 3. | P22: Claude (авт.) | Q22: 28.08.2026
A23: 22 | B23: 24 | C23: IEEE Standard for Learning Object Metadata | D23: Стандарт | E23: 2020 | F23: IEEE Std 1484.12.1-2020 | G23: https://ieeexplore.ieee.org/document/9262118/ | H23: https://ieeexplore.ieee.org/document/9262118/ | I23: IEEE SA; проверка на броя категории в ревизията от 2020 г. | J23: Критичен | K23: Твърдението за „девет категории“ произхожда от версията от 2002 г. Ревизията от 2020 г. има променена структура — ред 6 може да е верен за грешното издание. | L23: =COUNTIF('Ниво 2 Твърдения'!$C$2:$C$65,"*["&A23&"]*") | M23: Потвърдено | N23: IEEE Std 1484.12.1-2020 || НЯМА ДОСТЪП. ПРЕПОРЪКА: твърдението за деветте категории и четирите признака на Educational категорията не бива да стои без прочетен стандарт. Или се търси свободен източник, който описва схемата, или изречението се свежда до съществуването на международен стандарт за метаданни без изброяване на съдържанието му. || РЕШЕНО: съдържанието е потвърдено през свободното ръководство на 1EdTech/IMS за LOM v1.3. Записът трябва да сочи версията, която наистина е проверена. | O23: ОТМЕНЯМ по-ранното предупреждение: деветте категории от първо ниво важат и за ревизията от 2020 г. Остава да се провери съдържанието на Educational категорията (Ниво 2, ред 6). | P23: Claude (авт.) | Q23: 28.08.2026
A24: 23 | B24: 25 | C24: J. Biggs, C. Tang, G. Kennedy — Teaching for Quality Learning at University | D24: Книга | E24: 2022 | F24: 5-о изд., Open University Press | G24: https://www.mheducation.co.uk/teaching-for-quality-learning-at-university-5e-9780335250820-emea-group | H24: https://www.mheducation.co.uk/teaching-for-quality-learning-at-university-5e-9780335250820-emea-group | I24: Каталог на издателя/ISBN | J24: Среден | K24: Провери годината, изданието и състава на авторите за 5-о изд. | L24: =COUNTIF('Ниво 2 Твърдения'!$C$2:$C$65,"*["&A24&"]*") | M24: Потвърдено | N24: ISBN 9780335250820, McGraw Hill / Open University Press || НЯМА ДОСТЪП. ПРЕПОРЪКА: замяна с първоизточника на конструктивното съгласуване — Biggs, J. (1996). „Enhancing teaching through constructive alignment.“ Higher Education, 32(3), 347–364. Статия, не учебник, намира се далеч по-лесно. || ПРОВЕРЕН СВАЛЕНИЯТ ФАЙЛ: Enhancing_Teaching_Through_Constructive_Alignment.pdf е ПРЕЗЕНТАЦИЯ на PowerPoint от 2009 г. („Slide 1“, Acrobat PDFMaker for PowerPoint), 2332 думи слайдов текст, без резюме и без списък с литература. НЕ Е годна за цитиране в научен труд. Търси се статията Biggs (1996), Higher Education, 32(3), 347–364. || РЕШЕНО: свален е правилният файл Biggs1996_Article_EnhancingTeachingThroughConstr.pdf, Higher Education 32: 347–364. Учебникът от 2022 г. отпада. | O24: 5-о изд., Biggs, Tang, Kennedy. Годината 2022 да се сверя в каталога на издателя при финалната редакция. | P24: Claude (авт.) | Q24: 28.08.2026
A25: 24 | B25: 26 | C25: J. Sweller, J. van Merriënboer, F. Paas — Cognitive architecture… 20 years later | D25: Списание | E25: 2019 | F25: doi: 10.1007/s10648-019-09465-5 | G25: https://api.openalex.org/works/doi:10.1007/s10648-019-09465-5 | H25: https://api.openalex.org/works/doi:10.1007/s10648-019-09465-5 | I25: DOI | J25: Висок | K25: В тази статия авторите ревизират схващането за „полезно натоварване“ — формулировката в ред 11 трябва да съвпадне с ревизираната. | L25: =COUNTIF('Ниво 2 Твърдения'!$C$2:$C$65,"*["&A25&"]*") | M25: Потвърдено | N25: Educational Psychology Review, т. 31, кн. 2, с. 261–292, 2019 | O25: Точно съвпадение. | P25: Claude (авт.) | Q25: 28.08.2026
A26: 25 | B26: 27 | C26: L. Huang et al. — A survey on hallucination in LLMs | D26: Списание | E26: 2025 | F26: doi: 10.1145/3703155 | G26: https://arxiv.org/abs/2311.05232 | H26: https://arxiv.org/abs/2311.05232 | I26: DOI | J26: Среден | K26: Терминологична точност — „фактологични“ vs „faithfulness“ халюцинации (ред 22). | L26: =COUNTIF('Ниво 2 Твърдения'!$C$2:$C$65,"*["&A26&"]*") | M26: Потвърдено | N26: ACM TOIS, т. 43, кн. 2, с. 1–55 | O26: Онлайн 2024, книжка 2025 — годината 2025 в записа е защитима. | P26: Claude (авт.) | Q26: 28.08.2026
A27: 26 | B27: 28 | C27: L. Zheng et al. — Judging LLM-as-a-judge with MT-Bench and Chatbot Arena | D27: Конференция | E27: 2023 | F27: NeurIPS 2023 D&B; arXiv:2306.05685 | G27: https://arxiv.org/html/2306.05685v4 | H27: https://arxiv.org/html/2306.05685v4 | I27: arXiv | J27: Критичен | K27: Носи три процента (над 80, ~85, ~81), които се появяват два пъти в текста (редове 57 и 63) и трябва да съвпадат помежду си. | L27: =COUNTIF('Ниво 2 Твърдения'!$C$2:$C$65,"*["&A27&"]*") | M27: Потвърдено | N27: arXiv:2306.05685, NeurIPS 2023 D&B | O27: 13 автора, първи Lianmin Zheng — точно. | P27: Claude (авт.) | Q27: 28.08.2026
A28: 27 | B28: 29 | C28: M. D. Merrill — First principles of instruction | D28: Списание | E28: 2002 | F28: doi: 10.1007/BF02505024; т. 50, кн. 3, с. 43–59 | G28: https://api.openalex.org/works/doi:10.1007/bf02505024 | H28: https://api.openalex.org/works/doi:10.1007/bf02505024 | I28: DOI | J28: Висок | K28: Локаторът „с. 44–45“ не е проверим — няма достъп до пълния текст. 31.08.2026: локаторът е премахнат от текста; цитира се цялата статия (с. 43–59), която изцяло е посветена на петте принципа. | L28: =COUNTIF('Ниво 2 Твърдения'!$C$2:$C$65,"*["&A28&"]*") | M28: Потвърдено (ниво на статия) | N28: ETR&D, т. 50, кн. 3, с. 43–59, 2002 | O28: Точно съвпадение. Локаторът с. 44–45 остава за Ниво 2. | P28: Claude (авт.) | Q28: 28.08.2026
A29: 28 | B29: 31 | C29: O. Zawacki-Richter et al. — Systematic review of AI in higher education | D29: Списание | E29: 2019 | F29: doi: 10.1186/s41239-019-0171-0 | G29: https://link.springer.com/article/10.1186/s41239-019-0171-0 | H29: https://link.springer.com/article/10.1186/s41239-019-0171-0 | I29: DOI; отворен достъп | J29: Среден | K29: Периодът 2007–2018 и изводът за участието на педагози (ред 35). | L29: =COUNTIF('Ниво 2 Твърдения'!$C$2:$C$65,"*["&A29&"]*") | M29: Потвърдено | N29: IJETHE, т. 16, чл. 39, 2019 | O29: Четиримата автори съвпадат. Периодът 2007–2018 е потвърден (146 от 2656 публикации). | P29: Claude (авт.) | Q29: 28.08.2026
A30: 29 | B30: 32 | C30: Quality Matters — QM Higher Education Rubric, 7-о изд. | D30: Рубрика/стандарт | E30: 2023 | F30: qualitymatters.org | G30: https://educationaldevelopment.uams.edu/qualitymatters/qm-rubric | H30: https://educationaldevelopment.uams.edu/qualitymatters/qm-rubric | I30: Сайт на QM; официално описание на 7-о издание | J30: Критичен | K30: Числата „8 общи и 44 конкретни стандарта“ се менят между изданията (в 6-о изд. са 42) — ред 55. | L30: =COUNTIF('Ниво 2 Твърдения'!$C$2:$C$65,"*["&A30&"]*") | M30: Потвърдено | N30: QM HE Rubric, 7-о изд. | O30: Потвърдено: 8 общи и 44 конкретни ревизионни стандарта. Виж ред 55. | P30: Claude (авт.) | Q30: 28.08.2026
A31: 30 | B31: ОТПАДА | C31: R. C. Clark, R. E. Mayer — e-Learning and the Science of Instruction | D31: Книга | E31: 2024 | F31: 5-о изд., Wiley | G31: https://www.harvard.com/book/9781394177370 | H31: https://www.harvard.com/book/9781394177370 | I31: Каталог на Wiley; съдържание на изданието | J31: Критичен | K31: Втори по натовареност източник — 5 твърдения с локатори по глави (1, 4, 9, 12, 13, 21). Провери и годината на 5-о изд., и че номерата на главите отговарят на това издание. | L31: =COUNTIF('Ниво 2 Твърдения'!$C$2:$C$65,"*["&A31&"]*") | M31: Не се потвърждава | N31: Wiley, 5-о изд., ISBN 9781394177370 — 12.12.2023 г. || ПРОВЕРЕНА ЗАМЯНА (отхвърлена): scirp.org/pdf/psych_2023051914322531.pdf се оказва „Online Learning: A Cognitive Tool for Learning…“, A. Fenteng, сп. Psychology (SCIRP), 2023, doi 10.4236/psych.2023.145036. Друга тема, друг автор, не съдържа принципите на мултимедийното учене. НЕ Е годна замяна на Clark & Mayer. | O31: ГРЕШКА В ЗАПИСА: 5-о издание е публикувано на 12 декември 2023 г., не 2024. ДЕЙСТВИЕ: поправи годината на 2023 във всички препратки. || НАНЕСЕНО В НИП 28.08: годината става 2023. | P31: Claude (авт.) | Q31: 28.08.2026
A32: 31 | B32: 34 | C32: Регламент (ЕС) 2024/1689 (Акт за изкуствения интелект) | D32: Правен акт | E32: 2024 | F32: OJ L, 2024/1689, 12.7.2024 | G32: https://eur-lex.europa.eu/eli/reg/2024/1689/oj | H32: https://eur-lex.europa.eu/eli/reg/2024/1689/oj | I32: EUR-Lex | J32: Висок | K32: Твърдението за прозрачност при генерирано съдържание трябва да сочи конкретен член (чл. 50) — ред 50. | L32: =COUNTIF('Ниво 2 Твърдения'!$C$2:$C$65,"*["&A32&"]*") | M32: Потвърдено | N32: Регламент (ЕС) 2024/1689, OJ L 2024/1689, 12.7.2024 | O32: Приет 13.06.2024 — съвпада. Членът за прозрачност (чл. 50) да се посочи в текста (Ниво 2, ред 50). | P32: Claude (авт.) | Q32: 28.08.2026
A33: 32 | B33: 35 | C33: S. G. Ramezani, Z. S. Mostafavi — скала за акредитационни стандарти | D33: Списание | E33: 2025 | F33: doi: 10.1007/s10639-025-13587-5 | G33: https://api.openalex.org/works/doi:10.1007/s10639-025-13587-5 | H33: https://api.openalex.org/works/doi:10.1007/s10639-025-13587-5 | I33: DOI | J33: Нисък | K33: Стандартен запис. | L33: =COUNTIF('Ниво 2 Твърдения'!$C$2:$C$65,"*["&A33&"]*") | M33: Потвърдено | N33: Education and Information Technologies, т. 30, кн. 15, с. 21139–21187, 2025 | O33: Точно съвпадение. | P33: Claude (авт.) | Q33: 28.08.2026
A34: 33 | B34: 36 | C34: S. J. Warren et al. — Enhancing quality assurance through AI integration | D34: Списание | E34: 2026 | F34: Quality Assurance in Education, т. 34, кн. 2, с. 205–222 | G34: https://www.emerald.com/qae/article/34/2/205/1302250/Enhancing-quality-assurance-through-strategic | H34: https://www.emerald.com/qae/article/34/2/205/1302250/Enhancing-quality-assurance-through-strategic | I34: Сайт на Emerald; търсене по заглавие | J34: Висок | K34: Единственият запис в списъка на списание без DOI, при това с година 2026. Потвърди съществуването и допълни DOI. | L34: =COUNTIF('Ниво 2 Твърдения'!$C$2:$C$65,"*["&A34&"]*") | M34: Потвърдено | N34: QAE, т. 34, кн. 2, с. 205–222, 2026 | O34: Съществува. Автори S. J. Warren, E. Boston Vogt, B. Tincher, J. Yang. DOI: 10.1108/QAE-09-2024-0183 — ДЕЙСТВИЕ: добави го, това беше единственият запис на списание без DOI. || НАНЕСЕНО В НИП 28.08: добави doi: 10.1108/QAE-09-2024-0183. | P34: Claude (авт.) | Q34: 28.08.2026
A35: 34 | B35: 37 | C35: UNESCO — Recommendation on Open Educational Resources | D35: Препоръка (ЮНЕСКО) | E35: 2019 | F35: unesdoc.unesco.org/ark:/48223/pf0000383205 | G35: https://unesdoc.unesco.org/ark:/48223/pf0000383205 | H35: https://unesdoc.unesco.org/ark:/48223/pf0000383205 | I35: UNESDOC | J35: Нисък | K35: Стабилен източник. | L35: =COUNTIF('Ниво 2 Твърдения'!$C$2:$C$65,"*["&A35&"]*") | M35: Потвърдено | N35: UNESCO, 2019 | O35: Документът съществува. Самата ark-връзка да се отвори при финалната редакция — страницата се зарежда динамично и не се провери автоматично. | P35: Claude (авт.) | Q35: 28.08.2026
A36: 35 | B36: ОТПАДА | C36: X. Chen, Z. Hu, C. Wang — Empowering education development through AIGC | D36: Списание | E36: 2024 | F36: doi: 10.1007/s10639-024-12549-7 | G36: https://link.springer.com/content/pdf/10.1007/s10639-024-12549-7.pdf | H36: https://link.springer.com/content/pdf/10.1007/s10639-024-12549-7.pdf | I36: DOI | J36: Висок | K36: Най-често използваният чужд източник след [16] — 6 твърдения, част от които изглеждат като авторски синтез (редове 8, 23). | L36: =COUNTIF('Ниво 2 Твърдения'!$C$2:$C$65,"*["&A36&"]*") | M36: Потвърдено | N36: Education and Information Technologies, т. 29, кн. 13, с. 17485–17537, 2024 || НЯМА ДОСТЪП до пълния текст. ПРЕПОРЪКА: ред 19 се пренасочва към Wang и кол. 2024 (ESWA), който е свален и проверен; ред 37 вече е там; ред 45 се пренасочва към Wu, Wang и Wen 2026 (Acta Psychologica 266, 106874), който документира „excessive dependence on AI outputs“. Остава да носи само ред 16 (понятието AIGC) — или отпада изцяло. || ОТПАДА ИЗЦЯЛО. И четирите му места са прехвърлени към Bahroun и кол. 2023, Sustainability 15(17), 12983 — библиометричен и съдържателен преглед на генеративния ИИ в образованието, свободен достъп. Wang и кол. 2024 (ESWA) НЕ ставаше: „developments, such as generative AI, are absent from our sample articles“. | O36: X. Chen, Z. Hu, C. Wang — точно. | P36: Claude (авт.) | Q36: 28.08.2026
A37: 36 | B37: 41 | C37: Z. Liu et al. — COGENT | D37: Работилница (BEA 2025) | E37: 2025 | F37: Proc. BEA 2025 | G37: https://aclanthology.org/2025.bea-1.10/ | H37: https://aclanthology.org/2025.bea-1.10/ | I37: ACL Anthology | J37: Нисък | K37: Стандартен запис. | L37: =COUNTIF('Ниво 2 Твърдения'!$C$2:$C$65,"*["&A37&"]*") | M37: Потвърдено | N37: aclanthology.org/2025.bea-1.10, с. 129–143 | O37: Z. Liu, S. X. Yin, D. H.-L. Goh, N. F. Chen. DOI: 10.18653/v1/2025.bea-1.10. ДЕЙСТВИЕ: добави страници и DOI. || НАНЕСЕНО В НИП 28.08: добави pp. 129–143 и doi: 10.18653/v1/2025.bea-1.10. | P37: Claude (авт.) | Q37: 28.08.2026

Sheet Ниво 1 — всички 53
A1: № (текущ) | B1: Библиографски запис | C1: Тип | D1: Как е проверен | E1: Статус | F1: Линк / DOI | G1: Извадка или данни от източника | H1: Бележка | I1: Брой цитирания в текста | J1: Предишен ред | K1: Дата
A2: 1 | B2: А. Захариев, „Изкуственият интелект в образователната и научна степен „доктор“: дигитализация, регулация и кредитна акселерация“, в Сб. докл. Четвърта научно-практическа конференция с международно участие „Дигитална трансформация на образованието – проблеми и решения“, Русе, България, 2026, с. 15–23. | C2: Доклад в сборник (BG) | D2: Сборник на конференцията (PDF/ISBN); при липса — контакт с организатора или автора | E2: Потвърдено | F2: https://www.conf-dte.bg/docs/2026/p-2.pdf | G2: 2026_p-2.pdf, печ. стр. 15–23 | H2: Заглавие, автор (Андрей Захариев) и страници съвпадат. | I2: 2 | J2: Ниво 1 Източници!ред 2 | K2: 28.08.2026
A3: 2 | B3: Д. Димитранов и Г. Димитров, „Изкуственият интелект като инструмент за автоматизирано създаване на бази данни от тестови въпроси“, в Сб. докл. Четвърта научно-практическа конференция с международно участие „Дигитална трансформация на образованието – проблеми и решения“, Русе, България, 2026, с. 576–580. | C3: Доклад в сборник (BG) | D3: Сборник; проверка на числата 656 000 знака / 553 въпроса | E3: Потвърдено | F3: https://www.conf-dte.bg/docs/2026/p-100.pdf | G3: 2026_p-100.pdf, печ. стр. 576–580 | H3: Дилян Димитранов, Георги Димитров — съвпада. | I3: 6 | J3: Ниво 1 Източници!ред 3 | K3: 28.08.2026
A4: 3 | B4: Е. Даскалова, О. Попова, С. Стефанов, М. Пенчева и В. Стефанова, „Концептуален дизайн за базирана на изкуствен интелект платформа за обучение на студенти по дентална анатомия“, в Сб. докл. Четвърта научно-практическа конференция с международно участие „Дигитална трансформация на образованието – проблеми и решения“, Русе, България, 2026, с. 554–558. | C4: Доклад в сборник (BG) | D4: Сборник; проверка на списъка от петима автори | E4: Потвърдено | F4: https://www.conf-dte.bg/docs/2026/p-96.pdf | G4: 2026_p-96.pdf, печ. стр. 554–558 | H4: Петимата автори съвпадат, вкл. Весела Стефанова. | I4: 1 | J4: Ниво 1 Източници!ред 4 | K4: 28.08.2026
A5: 4 | B5: М. Дамесова, „Овладяване на сложни концепции чрез генеративен изкуствен интелект и дигитален storytelling“, в Сб. докл. Четвърта научно-практическа конференция с международно участие „Дигитална трансформация на образованието – проблеми и решения“, Русе, България, 2026, с. 717–721. | C5: Доклад в сборник (BG) | D5: Сборник | E5: Потвърдено | F5: https://www.conf-dte.bg/docs/2026/p-124.pdf | G5: 2026_p-124.pdf, печ. стр. 717–721 | H5: Милена Дамесова — съвпада. | I5: 1 | J5: Ниво 1 Източници!ред 5 | K5: 28.08.2026
A6: 5 | B6: М. Левунлиева, „ИИ в образованието – перспективата на педагога“, в Сб. докл. Четвърта научно-практическа конференция с международно участие „Дигитална трансформация на образованието – проблеми и решения“, Русе, България, 2026, с. 605–610. | C6: Доклад в сборник (BG) | D6: Сборник; проверка на извадката от 68 специалисти и на „трите оценъчни оси“ | E6: Потвърдено | F6: https://www.conf-dte.bg/docs/2026/p-106.pdf | G6: 2026_p-106.pdf, печ. стр. 605–610 | H6: Милена Левунлиева — съвпада. | I6: 1 | J6: Ниво 1 Източници!ред 6 | K6: 28.08.2026
A7: 6 | B7: М. Маркова, „Изкуственият интелект в помощ на ускореното учене: практически инструменти за преподаватели“, в Сб. докл. Четвърта научно-практическа конференция с международно участие „Дигитална трансформация на образованието – проблеми и решения“, Русе, България, 2026, с. 541–546. | C7: Доклад в сборник (BG) | D7: Сборник; проверка на диапазона 75–90 % | E7: Потвърдено | F7: https://www.conf-dte.bg/docs/2026/p-94.pdf | G7: 2026_p-94.pdf, печ. стр. 541–546 | H7: Мая Маркова — записът е верен. ВНИМАНИЕ: твърдението в ред 31 на Ниво 2 не се потвърждава. | I7: 2 | J7: Ниво 1 Източници!ред 7 | K7: 28.08.2026
A8: 7 | B8: С. Гафтанджиева и Р. Донева, „Генеративен изкуствен интелект в образованието: проблеми и решения“, Педагогика, т. 97, кн. 9, с. 1284–1297, 2025, doi: 10.53656/ped2025-9.04. | C8: Списание (BG) | D8: DOI резолвер; проверка на вторично цитираното число „една шеста“ | E8: Потвърдено | F8: https://journals.azbuki.bg/pedagogy/generativen-izkustven-intelekt-v-obrazovanieto-problemi-i-reseniya/view | G8: печ. стр. 1284–1297; doi 10.53656/ped2025-9.04 | H8: Педагогика, т. 97, кн. 9, 2025 — съвпада. | I8: 2 | J8: Ниво 1 Източници!ред 8 | K8: 28.08.2026
A9: 8 | B9: Ц. Василев, „Използване на изкуствен интелект в обучението – гледна точка на студент и преподавател“, в Сб. докл. Четвърта научно-практическа конференция с международно участие „Дигитална трансформация на образованието – проблеми и решения“, Русе, България, 2026, с. 24–32. | C9: Доклад в сборник (BG) | D9: Сборник; проверка дали докладът наистина прави преглед на ~130 източника | E9: Потвърдено | F9: https://www.conf-dte.bg/docs/2026/p-3.pdf | G9: 2026_p-3.pdf, печ. стр. 24–32 | H9: Цветомир Василев — съвпада. | I9: 2 | J9: Ниво 1 Източници!ред 9 | K9: 28.08.2026
A10: 9 | B10: Ц. Дуцова, „Някои аспекти на приложение на изкуствения интелект в образованието“, в Сб. докл. Трета национална научно-практическа конференция „Дигитална трансформация на образованието – проблеми и решения“, Русе, България, 2025, с. 472–478. | C10: Доклад в сборник (BG) | D10: Сборник | E10: Потвърдено | F10: https://www.conf-dte.bg/docs/2025/p-84.pdf | G10: 2025_p-84.pdf, печ. стр. 472–478 | H10: Цветанка Дуцова, Трета конференция 2025 — съвпада. | I10: 1 | J10: Ниво 1 Източници!ред 10 | K10: 28.08.2026
A11: 10 | B11: A. S. Doğruöz et al., "Challenges and recommendations for LLMs-as-a-judge in multilingual settings and low-resource languages," 2026, arXiv:2607.02235. | C11: Препринт | D11: arxiv.org/abs/2607.02235 — първо съществуване, после авторство | E11: Потвърдено | F11: https://arxiv.org/html/2607.02235v1 | G11: arXiv:2607.02235 — съществува | H11: Заглавието съвпада. Автори: A. S. Doğruöz, X. Liao, V. Blaschke, J. Prange, S. Li, D. I. Adelani и др. ДЕЙСТВИЕ: добави авторите — запис без автор е формално некоректен по IEEE. Числата 650/33 се потвърждават. || НАНЕСЕНО В НИП 28.08: добави „A. S. Doğruöz et al.“ пред заглавието. | I11: 3 | J11: Ниво 1 Източници!ред 11 | K11: 28.08.2026
A12: 11 | B12: A. Sangrà, D. Vlachopoulos, and N. Cabrera, "Building an inclusive definition of e-learning: An approach to the conceptual framework," The International Review of Research in Open and Distributed Learning, vol. 13, no. 2, pp. 145–159, 2012, doi: 10.19173/irrodl.v13i2.1161. | C12: Списание (IRRODL) | D12: PDF в downloaded_pdfs + DOI | E12: Потвърдено | F12: https://doi.org/10.19173/irrodl.v13i2.1161 | G12: „Building an Inclusive Definition of E-Learning: An Approach to the Conceptual Framework“ — Albert Sangrà, Dimitrios Vlachopoulos, Nati Cabrera, Universitat Oberta de Catalunya | H12: aupress-admin,+Sangra2.pdf — заглавие и автори съвпадат дословно с записа. | I12: 2 | J12: НОВ РЕД — липсваше | K12: 31.08.2026
A13: 12 | B13: C. Redecker, European Framework for the Digital Competence of Educators: DigCompEdu, Y. Punie, Ed. Luxembourg: Publications Office of the European Union, 2017, JRC107466. | C13: Рамков документ (ЕС) | D13: Свободно достъпен PDF на JRC | E13: Потвърдено | F13: https://joint-research-centre.ec.europa.eu/digcompedu_en | G13: JRC107466, Publications Office of the EU, 2017 | H13: Redecker, ред. Punie — съвпада. | I13: 2 | J13: Ниво 1 Източници!ред 13 | K13: 28.08.2026
... A54: 53 | B54: Quality Matters, QM Higher Education Rubric, 7th ed. Annapolis, MD, USA: Quality Matters, 2023. [Online]. Available: https://www.qualitymatters.org/qa-resources/rubric-standards/higher-ed-rubric | C54: Рубрика/стандарт | D54: Сайт на QM; официално описание на 7-о издание | E54: Потвърдено | F54: https://educationaldevelopment.uams.edu/qualitymatters/qm-rubric | G54: QM HE Rubric, 7-о изд. | H54: Потвърдено: 8 общи и 44 конкретни ревизионни стандарта. Виж ред 55. | I54: 5 | J54: Ниво 1 Източници!ред 30 | K54: 28.08.2026

Sheet Списък 42
A1: Нов № | B1: Библиографски запис | C1: Стар № | D1: Бележка
A2: 1 | B2: А. Захариев, „Изкуственият интелект в образователната и научна степен „доктор“: дигитализация, регулация и кредитна акселерация“, в Сб. докл. Четвърта научно-практическа конференция с международно участие „Дигитална трансформация на образованието – проблеми и решения“, Русе, България, 2026, с. 15–23. | C2: 1
A3: 2 | B3: Д. Димитранов и Г. Димитров, „Изкуственият интелект като инструмент за автоматизирано създаване на бази данни от тестови въпроси“, в Сб. докл. Четвърта научно-практическа конференция с международно участие „Дигитална трансформация на образованието – проблеми и решения“, Русе, България, 2026, с. 576–580. | C3: 2
A4: 3 | B4: Е. Даскалова, О. Попова, С. Стефанов, М. Пенчева и В. Стефанова, „Концептуален дизайн за базирана на изкуствен интелект платформа за обучение на студенти по дентална анатомия“, в Сб. докл. Четвърта научно-практическа конференция с международно участие „Дигитална трансформация на образованието – проблеми и решения“, Русе, България, 2026, с. 554–558. | C4: 3
A5: 4 | B5: М. Дамесова, „Овладяване на сложни концепции чрез генеративен изкуствен интелект и дигитален storytelling“, в Сб. докл. Четвърта научно-практическа конференция с международно участие „Дигитална трансформация на образованието – проблеми и решения“, Русе, България, 2026, с. 717–721. | C5: 4
A6: 5 | B6: М. Левунлиева, „ИИ в образованието – перспективата на педагога“, в Сб. докл. Четвърта научно-практическа конференция с международно участие „Дигитална трансформация на образованието – проблеми и решения“, Русе, България, 2026, с. 605–610. | C6: 5
A7: 6 | B7: М. Маркова, „Изкуственият интелект в помощ на ускореното учене: практически инструменти за преподаватели“, в Сб. докл. Четвърта научно-практическа конференция с международно участие „Дигитална трансформация на образованието – проблеми и решения“, Русе, България, 2026, с. 541–546. | C7: 6
A8: 7 | B8: С. Гафтанджиева и Р. Донева, „Генеративен изкуствен интелект в образованието: проблеми и решения“, Педагогика, т. 97, кн. 9, с. 1284–1297, 2025, doi: 10.53656/ped2025-9.04. | C8: 7
A9: 8 | B9: Ц. Василев, „Използване на изкуствен интелект в обучението – гледна точка на студент и преподавател“, в Сб. докл. Четвърта научно-практическа конференция с международно участие „Дигитална трансформация на образованието – проблеми и решения“, Русе, България, 2026, с. 24–32. | C9: 8
A10: 9 | B10: Ц. Дуцова, „Някои аспекти на приложение на изкуствения интелект в образованието“, в Сб. докл. Трета национална научно-практическа конференция „Дигитална трансформация на образованието – проблеми и решения“, Русе, България, 2025, с. 472–478. | C10: 9
A11: 10 | B11: A. S. Doğruöz et al., "Challenges and recommendations for LLMs-as-a-judge in multilingual settings and low-resource languages," 2026, arXiv:2607.02235. | C11: 10
A12: 11 | B12: A. Sangrà, D. Vlachopoulos, and N. Cabrera, "Building an inclusive definition of e-learning: An approach to the conceptual framework," The International Review of Research in Open and Distributed Learning, vol. 13, no. 2, pp. 145–159, 2012, doi: 10.19173/irrodl.v13i2.1161. | D12: НОВ ИЗТОЧНИК
A13: 12 | B13: AI-Generated Content Best Practices, v1.0, 1EdTech Consortium, Lake Mary, FL, USA, 2025. [Online]. Available: https://www.imsglobal.org/resource/AI-Generated_Content_Best_Practices/v1p0 | D13: НОВ ИЗТОЧНИК
A14: 13 | B14: C. Redecker, European Framework for the Digital Competence of Educators: DigCompEdu, Y. Punie, Ed. Luxembourg: Publications Office of the European Union, 2017, JRC107466. | C14: 12
A15: 14 | B15: D. Li et al., "From generation to judgment: Opportunities and challenges of LLM-as-a-judge," in Proc. 2025 Conference on Empirical Methods in Natural Language Processing (EMNLP), 2025, pp. 2757–2791, doi: 10.18653/v1/2025.emnlp-main.138. | C15: 13
A16: 15 | B16: D. S. Chai, H. S. Kim, K. N. Kim, Y. Ha, S. S. H. Shin, and S. W. Yoon, "Generative artificial intelligence in instructional system design," Human Resource Development Review, vol. 24, no. 4, pp. 388–417, 2025, doi: 10.1177/15344843251320256. | C16: 14
A17: 16 | B17: E. Dickey and A. Bejarano, "GAIDE: A framework for using generative AI to assist in course content development," in Proc. 2024 IEEE Frontiers in Education Conference (FIE), 2024, pp. 1–9, doi: 10.1109/FIE61694.2024.10893132. | C17: 15
A18: 17 | B18: E. Kasneci et al., "ChatGPT for good? On opportunities and challenges of large language models for education," Learning and Individual Differences, vol. 103, Art. no. 102274, 2023, doi: 10.1016/j.lindif.2023.102274. | C18: 16
A19: 18 | B19: E. Staneviciene and G. Žekienė, "The use of multimedia in the teaching and learning process of higher education: A systematic review," Sustainability, vol. 17, no. 19, Art. no. 8859, 2025, doi: 10.3390/su17198859. | C19: 17
A20: 19 | B20: F. Miao and W. Holmes, Guidance for Generative AI in Education and Research. Paris, France: UNESCO, 2023. [Online]. Available: https://www.unesco.org/en/articles/guidance-generative-ai-education-and-research | C20: 18
A21: 20 | B21: G. W. Choi, S. H. Kim, D. Lee, and J. Moon, "Utilizing generative AI for instructional design: Exploring strengths, weaknesses, opportunities, and threats," TechTrends, vol. 68, no. 4, pp. 832–844, 2024, doi: 10.1007/s11528-024-00967-w. | C21: 19
A22: 21 | B22: H. Wu, Z. Wang, and X. Wen, "Examining interactive AI-supported learning environments: The mediating role of AI metacognition and the moderating role of cognitive flexibility," Acta Psychologica, vol. 266, Art. no. 106874, 2026. | D22: НОВ ИЗТОЧНИК
A23: 22 | B23: H. Yao, W. Xu, J. Turnau, N. Kellam, and H. Wei, "Instructional agents: Reducing teaching faculty workload through multi-agent instructional design," in Proc. EACL 2026, vol. 1, 2026, pp. 4087–4109, doi: 10.18653/v1/2026.eacl-long.191. | C23: 20
A24: 23 | B24: H. Zhang, S. Wang, T.-H. Chen, Y. Zou, and A. E. Hassan, "An empirical study of obsolete answers on Stack Overflow," IEEE Transactions on Software Engineering, vol. 47, no. 4, pp. 850–862, 2021, doi: 10.1109/TSE.2019.2906315. | C24: 11 | D24: НОВ ИЗТОЧНИК
A25: 24 | B25: IEEE Standard for Learning Object Metadata, IEEE Std 1484.12.1-2020, IEEE, New York, NY, USA, 2020. | C25: 22
A26: 25 | B26: J. Biggs, "Enhancing teaching through constructive alignment," Higher Education, vol. 32, no. 3, pp. 347–364, 1996, doi: 10.1007/BF00138871. | C26: 23 | D26: НОВ ИЗТОЧНИК
A27: 26 | B27: J. Sweller, J. J. G. van Merriënboer, and F. Paas, "Cognitive architecture and instructional design: 20 years later," Educational Psychology Review, vol. 31, no. 2, pp. 261–292, 2019, doi: 10.1007/s10648-019-09465-5. | C27: 24
A28: 27 | B28: L. Huang et al., "A survey on hallucination in large language models: Principles, taxonomy, challenges, and open questions," ACM Transactions on Information Systems, vol. 43, no. 2, pp. 1–55, 2025, doi: 10.1145/3703155. | C28: 25
A29: 28 | B29: L. Zheng et al., "Judging LLM-as-a-judge with MT-Bench and Chatbot Arena," in Advances in Neural Information Processing Systems 36 (NeurIPS 2023), Datasets and Benchmarks Track, 2023. [Online]. Available: https://arxiv.org/abs/2306.05685 | C29: 26
A30: 29 | B30: M. D. Merrill, "First principles of instruction," Educational Technology Research and Development, vol. 50, no. 3, pp. 43–59, 2002, doi: 10.1007/BF02505024. | C30: 27
A31: 30 | B31: N. F. Liu et al., "Lost in the middle: How language models use long contexts," Transactions of the Association for Computational Linguistics, vol. 12, pp. 157–173, 2024, doi: 10.1162/tacl_a_00638. | D31: НОВ ИЗТОЧНИК
A32: 31 | B32: O. Zawacki-Richter, V. I. Marín, M. Bond, and F. Gouverneur, "Systematic review of research on artificial intelligence applications in higher education — where are the educators?," International Journal of Educational Technology in Higher Education, vol. 16, Art. no. 39, 2019, doi: 10.1186/s41239-019-0171-0. | C32: 28
A33: 32 | B33: Quality Matters, QM Higher Education Rubric, 7th ed. Annapolis, MD, USA: Quality Matters, 2023. [Online]. Available: https://www.qualitymatters.org/qa-resources/rubric-standards/higher-ed-rubric | C33: 29
A34: 33 | B34: R. E. Mayer, "Evidence-based principles for how to design effective instructional videos," Journal of Applied Research in Memory and Cognition, vol. 10, no. 2, pp. 229–240, 2021, doi: 10.1016/j.jarmac.2021.03.007. | D34: НОВ ИЗТОЧНИК
A35: 34 | B35: Regulation (EU) 2024/1689 of the European Parliament and of the Council of 13 June 2024 laying down harmonised rules on artificial intelligence (Artificial Intelligence Act), OJ L, 2024/1689, 12.7.2024. [Online]. Available: https://eur-lex.europa.eu/eli/reg/2024/1689/oj | C35: 31
A36: 35 | B36: S. G. Ramezani and Z. S. Mostafavi, "Developing and validating a comprehensive scale for accreditation standards and quality assurance in e-learning institutions," Education and Information Technologies, vol. 30, no. 15, pp. 21139–21187, 2025, doi: 10.1007/s10639-025-13587-5. | C36: 32
A37: 36 | B37: S. J. Warren, E. Boston Vogt, B. Tincher, and J. Yang, "Enhancing quality assurance through strategic artificial intelligence integration: A framework for higher education digital transformation," Quality Assurance in Education, vol. 34, no. 2, pp. 205–222, 2026, doi: 10.1108/QAE-09-2024-0183. | C37: 33
A38: 37 | B38: UNESCO, Recommendation on Open Educational Resources (OER). Paris, France: UNESCO, 2019. [Online]. Available: https://unesdoc.unesco.org/ark:/48223/pf0000383205 | C38: 34
A39: 38 | B39: W. X. Zhao et al., "A survey of large language models," 2023, arXiv:2303.18223. | D39: НОВ ИЗТОЧНИК
A40: 39 | B40: Y. Gao et al., "Retrieval-augmented generation for large language models: A survey," 2023, arXiv:2312.10997. | D40: НОВ ИЗТОЧНИК
A41: 40 | B41: Z. Bahroun, C. Anane, V. Ahmed, and A. Zacca, "Transforming education: A comprehensive review of generative artificial intelligence in educational settings through bibliometric and content analysis," Sustainability, vol. 15, no. 17, Art. no. 12983, 2023, doi: 10.3390/su151712983. | D41: НОВ ИЗТОЧНИК
A42: 41 | B42: Z. Liu, S. X. Yin, D. H.-L. Goh, and N. F. Chen, "COGENT: A curriculum-oriented framework for generating grade-appropriate educational content," in Proc. 20th Workshop on Innovative Use of NLP for Building Educational Applications (BEA 2025), 2025, pp. 129–143, doi: 10.18653/v1/2025.bea-1.10. | C42: 36
A43: 42 | B43: Z. Wang, S.-Y. Gong, S. Xu, and X.-E. Hu, "Elaborated feedback and learning: Examining cognitive and motivational influences," Computers & Education, vol. 136, pp. 130–140, 2019, doi: 10.1016/j.compedu.2019.04.003. | D43: НОВ ИЗТОЧНИК

Sheet Ниво 2 Твърдения
A1: № | B1: Раздел | C1: Източник(ци) | D1: Източник(ци) — нови № | E1: Локатор в текста | F1: Твърдение (както е в документа) | G1: Тип на проверката | H1: Какво точно се потвърждава | I1: Приоритет | J1: Статус | K1: Намерено на (стр./раздел) | L1: Линк към проверения текст | M1: Извадка от източника (дословно) | N1: Бележка / действие | O1: Проверил | P1: Дата
A2: 1 | B2: 1.1 | C2: [30] | D2: заменен | E2: гл. 1 | F2: Clark и Mayer дефинират електронното обучение като обучение, доставяно чрез цифрово устройство, чието предназначение е да подпомага ученето, като изрично подчертават, че определящият признак не е технологията носител, а съчетанието от учебно съдържание и педагогически методи за неговото представяне [30, гл. 1]. | G2: Дефиниция | H2: Clark & Mayer, 5-о изд., гл. 1: дали дефиницията е такава и дали изрично се подчертава, че носителят не е определящият признак. | I2: Среден | J2: Потвърдено | K2: Sangrà, Vlachopoulos и Cabrera 2012, IRRODL 13(2), 145–159 — ЗАМЕСТИТЕЛ на [30, гл. 1] | L2: https://www.irrodl.org/index.php/irrodl/article/view/1161 | M2: Консенсусната дефиниция от Delphi проучването: „E-learning is an approach to teaching and learning, representing all or part of the educational model applied, that is based on the use of electronic media and devices as tools for improving access to training, communication and interaction and that facilitates the adoption of new ways of understanding and developing learning.“ Статията разграничава четири категории дефиниции: technology-driven, delivery-system-oriented, communication-oriented и educational-paradigm-oriented. | N2: ПОКРИВА СЕ ИЗЦЯЛО и по-добре от очакваното. Дефиницията определя е-обучението като ПОДХОД към преподаването и ученето, представящ приложения образователен модел, а електронните средства са „tools“. Това е точно тезата, че определящият признак е моделът, а не технологията — при това по консенсус на международен експертен панел, а не като едната страна на спора Кларк–Козма. Clark 1994 СТАВА ИЗЛИШЕН. | O2: Claude (авт.) | P2: 29.08.2026
A3: 2 | B3: 1.1 | C3: [12] | D3: [13] | E3: обл. 2 | F3: Значимостта на работата с дигитални ресурси за съвременния преподавател е призната и на рамково равнище: в европейската рамка за дигитална компетентност на преподавателите DigCompEdu подборът, създаването, модифицирането и управлението на дигитални ресурси са обособени като самостоятелна компетентностна област [12, обл. 2]. | G3: Рамков документ | H3: DigCompEdu: дали област 2 се нарича „Дигитални ресурси“ и обхваща подбор, създаване/модифициране и управление. | I3: Висок | J3: Потвърдено | K3: DigCompEdu, област 2 | L3: https://publications.jrc.ec.europa.eu/repository/bitstream/JRC107466/pdf_digcomedu_a4_final.pdf | M3: Област 2 „Digital Resources“ с подкомпетентности 2.1 Selecting digital resources, 2.2 Creating and modifying digital resources, 2.3 Managing, protecting and sharing digital resources. | N3: Потвърдено точно: подборът, създаването/модифицирането и управлението са обособени в самостоятелна област. | O3: Claude (авт.) | P3: 28.08.2026
A4: 3 | B4: 1.1 | C4: [30] | D4: заменен | E4: гл. 4 и 9 | F4: Изследванията върху мултимедийното учене показват, че комбинирането на словесна и визуална информация по правило води до по-добри учебни резултати от представянето само на текст, но единствено при спазване на установени принципи на дизайна — например съгласуваност между текст и изображение и изключване на несъщественото съдържание; в противен случай мултимедията може да затрудни, а не да подпомогне ученето [30, гл. 4 и 9]. | G4: Емпирично обобщение | H4: Гл. 4 и 9 на 5-о изд.: принцип на съгласуваност и изключване на несъщественото; дали източникът твърди и обратния ефект (мултимедия, която пречи). | I4: Висок | J4: Потвърдено | K4: Mayer 2021, JARMAC 10(2), 229–240 — ЗАМЕСТИТЕЛ на [30, гл. 4 и 9] | L4: https://www.sciencedirect.com/science/article/pii/S2211368121000231 | M4: „students learn better when extraneous comments and unneeded visual material are excluded (i.e., coherence principle)“; „Multimedia — Present words and graphics rather than words alone“; и за вредата: „Extraneous processing refers to cognitive processing during learning that does not serve the instructional objective of the lesson; it can be caused by poor instructional design, such as including extraneous graphics and text in the lesson.“ | N4: ПОКРИВА СЕ ИЗЦЯЛО от достъпен източник, включително частта „в противен случай мултимедията може да затрудни ученето“. Готово за замяна на локатора [30, гл. 4 и 9]. | O4: Claude (авт.) | P4: 29.08.2026
A5: 4 | B5: 1.1 | C5: [17] | D5: [18] | F5: Систематичните прегледи на използването на мултимедия във висшето образование потвърждават както широкото ѝ навлизане, така и зависимостта на ефектите от качеството на дидактическия дизайн [17]. | G5: Обобщение на преглед | H5: Дали прегледът наистина установява зависимост на ефектите от качеството на дидактическия дизайн, а не само разпространение. | I5: Среден | J5: Потвърдено | K5: [17] MDPI Sustainability 17(19):8859 | L5: https://www.mdpi.com/2071-1050/17/19/8859 | M5: „The integration of multimedia technologies into higher education is becoming increasingly widespread“; „multimedia tools enhance student engagement, motivation, and performance when integrated with clear pedagogical strategies“; „The effective implementation of multimedia tools requires a balance between technological innovation and pedagogical validity“. | N5: И двете части се потвърждават — навлизането и зависимостта от качеството на дизайна. | O5: Claude (авт.) | P5: 28.08.2026
A6: 5 | B6: 1.1 | C6: [34] | D6: [37] | F6: Значението на този режим е признато на международно равнище с препоръката на ЮНЕСКО за отворените образователни ресурси, която обвързва отвореното лицензиране с достъпа до качествено образование и с изграждането на капацитет за създаване, адаптиране и споделяне на такива ресурси [34]. | G6: Нормативен документ | H6: Дали Препоръката обвързва отвореното лицензиране с достъп до качествено образование И с изграждане на капацитет. | I6: Среден | J6: Потвърдено | K6: [34] UNESCO OER Recommendation, 2019 — свален PDF | L6: https://unesdoc.unesco.org/ark:/48223/pf0000383205 | M6: „Open Educational Resources (OER) can support quality education that is equitable, inclusive, open and participatory“; „Capacity building: developing the capacity of all key education stakeholders to create, access, re-use, re-purpose, adapt, and redistribute OER, as well as to use and apply open licenses“. | N6: Потвърдено по свалния от теб PDF. И двата елемента са налице — обвързването с качественото образование и изграждането на капацитет. | O6: Claude (авт.) | P6: 28.08.2026
A7: 6 | B7: 1.1 | C7: [22] | D7: [24] | F7: Международният стандарт за метаданни на учебни обекти определя структура от девет категории описателни характеристики, сред които образователната категория включва точно признаците, разгледани по-горе: вид на ресурса, равнище на интерактивност, целева аудитория и типично учебно време [22]. | G7: Точна структура | H7: Дали IEEE Std 1484.12.1-2020 определя девет категории и дали образователната включва точно четирите изброени признака. Внимание: „девет категории“ е от версията 2002 г. | I7: Висок | J7: Потвърдено | K7: 1EdTech/IMS Meta-data Best Practice Guide за IEEE 1484.12.1, v1.3 | L7: https://www.imsglobal.org/metadata/mdv1p3/imsmd_bestv1p3.html | M7: Деветте категории от първо ниво: General, Life Cycle, Meta-Metadata, Technical, Educational, Rights, Relation, Annotation, Classification. Категория 5 Educational съдържа Interactivity Type, Learning Resource Type, Interactivity Level, Intended End User Role, Context, Typical Age Range, Difficulty, Typical Learning Time. | N7: ПОТВЪРДЕНО чрез свободно достъпно авторитетно описание. И четирите признака, които изброяваш, се откриват: вид на ресурса (Learning Resource Type), равнище на интерактивност (Interactivity Level), целева аудитория (Intended End User Role / Typical Age Range) и типично учебно време (Typical Learning Time). ВНИМАНИЕ: ръководството описва версията от 2002 г. Или смени записа на 1484.12.1-2002, или цитирай ръководството отделно за съдържанието. | O7: Claude (авт.) | P7: 29.08.2026
A8: 7 | B8: 1.1 | C8: [11] | D8: [23] | F8: В областите с бавно развиващо се фундаментално знание учебният материал може да остане валиден десетилетия; в бързо развиващите се технологични области — например разработката на софтуер — препоръчаните практики, версиите на инструментите и дори терминологията се променят в рамките на месеци, при това по публично обявен график: широко използвани софтуерни рамки издават основни версии веднъж или два пъти годишно, а поддръжката на всяка версия е ограничена във времето [11]. | G8: Обобщение по един случай | H8: Дали източникът поддържа общото твърдение за „широко използвани софтуерни рамки“ — той описва само Angular. Обмисли отпадане или замяна с общ източник. | I8: Критичен | J8: Потвърдено | K8: Zhang, Wang, Chen, Zou и Hassan, IEEE TSE 47(4), 850–862 — ЗАМЕСТИТЕЛ на [11] Angular | L8: https://arxiv.org/abs/1903.12282 | M8: „More than half of the obsolete answers (58.4%) were probably already obsolete when they were first posted“; едва 20,5 % от остарелите отговори някога биват обновявани. Тагове като node.js, ajax, android и objective-c са по-податливи на остаряване. | N8: ГОТОВО ЗА НАНАСЯНЕ (Word държи документа отворен). Angular отпада. Новата формулировка твърди същото — че техническото съдържание остарява бързо — но с емпирично изследване върху 15 години данни вместо с документация на един продукт. Двете числа са дословни. | O8: Claude (авт.) | P8: 29.08.2026
A9: 8 | B9: 1.1 | C9: [35] | D9: заменен | F9: Четвъртата ос, придобила значение едва през последните години, е произходът на съдържанието: създадено изцяло от преподавател или автор, адаптирано от съществуващи ресурси, или генерирано с помощта на инструменти с изкуствен интелект [35]. | G9: Приписване | H9: Дали [35] наистина обособява „произход на съдържанието“ като ос на класификация, или това е авторски синтез. | I9: Висок | J9: Потвърдено | K9: 1EdTech AI-Generated Content Best Practices v1.0 (2025) — ЗАМЕСТИТЕЛ на [35] | L9: https://www.imsglobal.org/resource/AI-Generated_Content_Best_Practices/v1p0 | M9: Документът степенува съдържанието по произход в пет равнища: „Human-Created, GenAI-Assisted“, „Human-Led, GenAI-Enhanced“, „GenAI-Co-Created, Human-Guided“, „GenAI-Dominant, Human-Supervised“ и „Fully AI-Generated — GenAI autonomously generates and publishes content with minimal or no human oversight“. | N9: РЕШЕНО. Класификацията по произход НЕ е авторска — тя съществува в документ на стандартизационен консорциум, при това по-подробна от твоята. НАНЕСЕНО В НИП 29.08: четвъртата ос вече препраща към петте равнища на 1EdTech. Заместителят е с временен маркер [X1EDTECH] до преномерирането. | O9: Claude (авт.) | P9: 29.08.2026
A10: 9 | B10: 1.2 | C10: [27] | D10: [29] | E10: — (локаторът е премахнат) | F10: Като обобщение на общоприетите дидактически постановки Merrill извежда пет първи принципа на обучението: ученето се улеснява, когато обучаемият е въвлечен в решаването на реални задачи; когато наличното му знание се активира като основа за новото; когато новото знание му се демонстрира; когато той го прилага самостоятелно; и когато го интегрира в собствената си практика [27, с. 44–45]. | G10: Точен локатор | H10: Merrill 2002, с. 44–45: дали петте принципа са формулирани там и в този ред/смисъл. | I10: Висок | J10: Потвърдено (без локатор) | K10: Springer / OpenAlex — резюме и пълен запис на статията; страничният локатор не е проверим | L10: https://link.springer.com/article/10.1007/BF02505024 | M10: „Learning is promoted when learners are engaged in solving real-world problems“; „…when existing knowledge is activated as a foundation for new knowledge“; „…when new knowledge is demonstrated to the learner“; „…when new knowledge is applied by the learner“; „…when new knowledge is integrated into the learner's world“. | 31.08.2026: PDF на статията не е достъпен (MIT, pbworks и авторският сайт са блокирани). Петте принципа се потвърждават дословно от резюмето, но „с. 44–45“ не може да бъде проверен — локаторът е премахнат и в МТ, и в НИП; цитира се цялата статия [29]. | N10: Петте принципа се потвърждават дословно и в същия ред. Локаторът „с. 44–45“ да се сверя по PDF-а — статията е с. 43–59, а принципите се появяват и в резюмето. | O10: Claude (авт.) | P10: 28.08.2026
A11: 10 | B11: 1.2 | C11: [23] | D11: [25] | F11: Изискването за съответствие с целите има и утвърдена конструктивна рамка: принципът на конструктивното съгласуване, при който учебните цели, учебните дейности и средствата за оценяване се проектират като едно свързано цяло — тръгва се от намерените учебни резултати и от тях се извеждат както дейностите, така и проверката [23]. | G11: Концепция | H11: Biggs & Tang: конструктивно съгласуване — дали формулировката „тръгва се от намерените учебни резултати“ съответства. | I11: Среден | J11: Потвърдено | K11: Biggs 1996, Higher Education 32, 347–364 — ЗАМЕСТИТЕЛ на [23] | L11: https://link.springer.com/article/10.1007/BF00138871 | M11: „Constructive alignment represents a marriage of the two thrusts, constructivism being used as a framework to guide decision-making at all stages in instructional design: in deriving curriculum objectives in terms of performances that represent a suitably high cognitive level, in deciding teaching/learning activities judged to elicit those performances, and to assess and summatively report student performance. The performances of understanding nominated in the objectives are thus used to systematically align the teaching methods and the assessment.“ | N11: ПРАВИЛНИЯТ ФАЙЛ Е СВАЛЕН и потвърждава реда дословно, включително че се тръгва от учебните резултати и от тях се извеждат дейностите и оценяването. Учебникът [23] отпада, заменя се със статията от 1996 г. | O11: Claude (авт.) | P11: 29.08.2026
A12: 11 | B12: 1.2 | C12: [24] | D12: [26] | F12: Тя разграничава вътрешно натоварване, произтичащо от сложността на самия учебен материал, външно натоварване, породено от начина на представяне, и полезно натоварване, свързано с изграждането на трайни знания; централното ѝ предписание е външното натоварване да се минимизира, за да остане капацитетът на работната памет за същинското учене [24]. | G12: Терминология | H12: Sweller et al. 2019: трите вида натоварване и предписанието. Внимание — в тази статия понятието „полезно натоварване“ е ревизирано; формулировката трябва да е съгласувана с нея. | I12: Висок | J12: Потвърдено | K12: [24] Sweller и кол. 2019, EPR 31(2) | L12: https://link.springer.com/article/10.1007/s10648-019-09465-5 | M12: „Germane cognitive load was defined as the cognitive load required to learn, which refers to the working memory resources that are devoted to dealing with intrinsic cognitive load rather than extraneous cognitive load.“ И изрично: „This characterisation of germane cognitive load is a departure from the 1998 paper… Currently, we assume that rather than contributing to the total load, germane cognitive load redistributes working memory resources.“ Предписанието: „cognitive processing irrelevant to learning is minimised and cognitive processing germane to learning is optimised.“ | N12: ВАЖНО: описанието на полезното натоварване като „свързано с изграждането на трайни знания“ беше по СТАРАТА формулировка от 1998 г. Статията от 2019 г. изрично я ревизира. НАНЕСЕНО В НИП 28.08: полезното натоварване вече е описано като преразпределяне на ресурсите на работната памет, а предписанието е дадено с двете му части. || ЗАТВОРЕН. Текстът вече описва полезното натоварване по ревизираната формулировка от 2019 г. — преразпределяне на ресурсите на работната памет. Твърдението и източникът съвпадат. | O12: Claude (авт.) | P12: 29.08.2026
A13: 12 | B13: 1.2 | C13: [30] | D13: [38] | E13: гл. 13 | F13: Изследванията върху мултимедийното учене потвърждават ползата от сегментирането на съдържанието и от предварителната подготовка с основните понятия [30, гл. 13]. | G13: Емпирично обобщение | H13: Гл. 13: сегментиране и предварителна подготовка с основни понятия (pre-training principle). | I13: Среден | J13: Потвърдено | K13: JARMAC 10(2), печ. с. 233 (Табл. 3) и с. 235–236 — проверено по изтегления PDF | L13: https://doi.org/10.1016/j.jarmac.2021.03.007 | M13: Раздел „Principles for Managing Essential Processing: Segmenting, Pre-training, and Modality Principles“ (с. 235). СЕГМЕНТИРАНЕ: „…one way to manage essential processing is to break a complex presentation into manageable segments whose pace is controlled by the learner.“ | „This type of segmenting improved transfer test performance across two experiments (Mayer et al., 2018, 2019), and overall across 7 out of 7 experiments, various forms of segmenting of slideshows resulted in better transfer test performance as compared to a continuous presentation, yielding a median effect size of d = 0.67 (Mautone & Mayer, 2007; Mayer & Chandler, 2001; Mayer, Dow, & Mayer, 2003; Sung & Mayer, 2013).“ | „Segmenting allows the learner to build a mental representation of one part of the material before moving on to the next.“ (с. 235) ПРЕДВАРИТЕЛНА ПОДГОТОВКА: „The second way to manage essential processing listed in Table 3 is to provide pre-training in the names and characteristics of the key elements in the lesson.“ | „Across two experiments, students who received this pre-training before the brakes lesson performed better on a transfer than those who did not receive pre-training, with a median effect size of d = 0.85 (Mayer et al., 2002).“ (с. 235–236) Таблица 3, ред „MANAGE ESSENTIAL PROCESSING“: „Segmenting — Break a complex lesson into progressive parts under the control of the learner“; „Pre-training — Provide pre-training in the names and characteristics of key concept“ (с. 233). | N13: ПОКРИВА СЕ ИЗЦЯЛО. Готово за замяна. || 31.08.2026: приложено в текста, абз. 55, текуща номерация [38]. || 31.08.2026: предишната извадка беше два откъслека от резюмето и таблицата и не позволяваше да се прецени дали ползата е ДОКАЗАНА. Заменена с пасажите от текста, които дават броя експерименти и размерите на ефекта (d = 0,67 за сегментирането, d = 0,85 за предварителната подготовка). Предстои добавяне на локатор [38, с. 235–236] в текста. | O13: Claude (авт.) | P13: 31.08.2026
A14: 13 | B14: 1.2 | C14: [12] | D14: [13] | E14: обл. 2 | F14: В европейската рамка DigCompEdu изборът и създаването на дигитални ресурси изрично се обвързват с отчитането на конкретната учебна цел, контекста и характеристиките на обучаемите [12, обл. 2]. | G14: Рамков документ | H14: DigCompEdu, област 2: обвързване на избора на ресурси с учебната цел, контекста и характеристиките на обучаемите. | I14: Среден | J14: Потвърдено | K14: DigCompEdu, 2.1 и 2.2 | L14: https://publications.jrc.ec.europa.eu/repository/bitstream/JRC107466/pdf_digcomedu_a4_final.pdf | M14: „To consider the specific learning objective, context, pedagogical approach, and learner group, when selecting digital resources and planning their use.“ Същото условие се повтаря и при създаването на ресурси. | N14: Потвърдено дословно, включително трите елемента — учебна цел, контекст и характеристики на обучаемите. | O14: Claude (авт.) | P14: 28.08.2026
A15: 14 | B15: 1.2 | C15: [30] | D15: [37, гл. 13] + [48] | E15: гл. 12 | F15: Изискванията към упражненията и проверката са няколко: взаимодействията да са достатъчно на брой за постигане на целта; задачите да отразяват реалните дейности, за които обучаемият се подготвя; и обратната връзка да бъде съдържателна — да обяснява защо отговорът е верен или грешен, а не само да констатира резултата [30, гл. 12]. | G15: Списък изисквания | H15: Гл. 12: трите изисквания — брой взаимодействия, автентичност на задачите, обяснителна обратна връзка. | I15: Среден | J15: Потвърдено | K15: Wang и кол. 2019, Computers & Education 136, 130–140 | L15: https://www.sciencedirect.com/science/article/abs/pii/S036013151930082X | M15: „elaborated feedback is not necessarily more effective than simple feedback“; „computer-based feedback did not always promote learning and might even hinder learning“. Резултат: „Detailed explanation promoted learners' feedback perception and transfer performance IN THE CONSTRUCTED-RESPONSE ITEM CONDITION“ — тоест ефектът зависи от формата на задачата. | N15: ВАЖНО: този източник не подкрепя безусловното изискване „обратната връзка да обяснява защо“. Той показва, че ефектът е УСЛОВЕН. Ако се използва, изречението трябва да стане условно. Частта „задачите да отразяват реалните дейности“ вече е покрита от [27] Merrill, принцип 1. Частта „взаимодействията да са достатъчно на брой“ остава без източник. || ЗАТВОРЕН. Изречението вече е условно и възпроизвежда точно находката на [42]: подробното обяснение помага при задачи със свободен отговор, но не и при въпроси с множествен избор. || 31.08.2026: приложено в текста, абз. 57, текуща номерация [37, гл. 13] + [48]. | O15: Claude (авт.) | P15: 29.08.2026
A16: 15 | B16: 1.2 | C16: [21] | D16: [53] | F16: Сравнителният анализ на ръководни документи за качество на онлайн учебни материали от различни образователни контексти показва, че описаните дотук педагогически и визуални изисквания се систематизират в проверими насоки за дизайн и оценяване [21] — което подготвя прехода от изисквания към критерии, предмет на следващия етап от изследването. | G16: Обобщение на преглед | H16: Дали сравнителният анализ извежда проверими насоки за дизайн и оценяване. | I16: Среден | J16: Потвърдено | K16: QM Higher Education Rubric, 7-о изд. — страница на стандартите | L16: https://www.qualitymatters.org/qa-resources/rubric-standards/higher-ed-rubric | M16: „A set of eight General Standards and 44 Specific Review Standards used to evaluate the design of online and hybrid courses.“ | Осемте общи стандарта: „Course Overview and Introduction; Learning Objectives (Competencies); Assessment and Measurement; Instructional Materials; Learning Activities and Learner Interaction; Course Technology; Learner Support; Accessibility and Usability.“ | „The Rubric is also used to assess the level to which a course meets Standards and highlight areas for improvement.“ | N16: Taylor & Francis връща 403 при автоматично четене. Нужен е достъп през университета. || ЗАТВОРЕН. Пренасочен към [32] Quality Matters — осем общи и четиридесет и четири конкретни ревизионни стандарта. Недостъпният du Preez отпадна от списъка. || 31.08.2026: приложено в текста, абз. 60, текуща номерация [53]. || 31.08.2026: редът беше БЕЗ НИТО ЕДНА ИЗВАДКА (старият източник [21] du Preez връщаше 403). Попълнена извадка от действително използвания източник [53] Quality Matters. | O16: Claude (авт.) | P16: 31.08.2026
A17: 16 | B17: 1.3 | C17: [35] | D17: заменен | F17: В литературата създаваното от тях съдържание се обозначава с обобщаващото понятие AI-генерирано съдържание (AI-generated content, AIGC), а изследванията върху приложението му в образованието нарастват рязко след масовото навлизане на диалоговите системи от типа на ChatGPT в края на 2022 г. [35]. | G17: Терминология + тенденция | H17: Дали [35] използва понятието AIGC и дали документира рязък ръст след края на 2022 г. | I17: Среден | J17: Потвърдено | K17: Bahroun, Anane, Ahmed и Zacca 2023, Sustainability 15(17), 12983 | L17: https://www.mdpi.com/2071-1050/15/17/12983 | M17: „the analysis reveals significant and exponential growth in GAI research in 2023“; „The rise of AI was sparked in November 2022, when U.S. company OpenAI released ChatGPT“; „applications of GAI encompass assessment, personalized learning support, and intelligent tutoring systems“. | N17: ЗАМЕНЕН ИЗТОЧНИК. [35] отпада. Ръстът е потвърден дословно и е обвързан с ноември 2022 г. „AIGC“ отпада от текста, защото новият източник работи с понятието генеративен изкуствен интелект (GAI) — цитиране за термин, който източникът не използва, е същата грешка като на ред 17. | O17: Claude (авт.) | P17: 29.08.2026
A18: 17 | B18: 1.3 | C18: [16] | D18: [17] | F18: След допълнителна настройка, включително чрез обратна връзка от хора, тези модели придобиват способността да водят диалог, да следват инструкции и да произвеждат свързан, стилистично издържан текст по практически всякаква тема [16]. | G18: Техническо описание | H18: Дали Kasneci et al. описват дообучението с човешка обратна връзка като източник на диалогова способност и следване на инструкции. | I18: Среден | J18: Потвърдено | K18: [16] ИЗДАДЕНА версия, Learning and Individual Differences 103, 102274 | L18: https://www.sciencedirect.com/science/article/pii/S1041608023000195 | M18: „transformer architecture, introduced in Vaswani et al. (2017), uses the self-attention mechanism“; „the use of pre-training, where a language model is first trained on a large dataset before being fine-tuned“. В целия текст НЯМА reinforcement learning from human feedback, instruction tuning или предсказване на следващ токен. | N18: Издадената версия потвърждава находката от препринта. Пренаписването от 28.08 е правилно и остава. || ЗАТВОРЕН. Изречението вече твърди само трансформер, самовнимание, предварително обучение и последваща настройка — всичките дословно в [17]. Проверено и срещу издадената версия. | O18: Claude (авт.) | P18: 29.08.2026
A19: 18 | B19: 1.3 | C19: [16] | D19: [17] | F19: За преподавателите те могат да подпомагат подготовката на учебни текстове, резюмета, примери, тестови въпроси и материали с различна степен на сложност, съобразени с конкретна аудитория; за обучаемите — да предоставят обяснения, отговори на въпроси и персонализирана подкрепа при самоподготовка [16]. | G19: Списък приложения | H19: Дали изброените приложения за преподаватели и обучаеми са в източника. | I19: Среден | J19: Потвърдено | K19: [16] — пълен текст | L19: https://opus.bibliothek.uni-augsburg.de/opus4/files/109030/109030.pdf | M19: „Teachers can use large language models to create personalized learning experiences for their students… suggest materials that align with the student's specific learning needs.“ / „Large language models can be used to generate summaries and outlines of texts.“ | N19: Приложенията за преподаватели и обучаеми се потвърждават дословно (виж извадката). | O19: Claude (авт.) | P19: 28.08.2026
A20: 19 | B20: 1.3 | C20: [35] | D20: заменен | F20: Систематичните прегледи регистрират приложения по цялата верига на учебния процес — от планирането на курсове през създаването на съдържание до оценяването и обратната връзка [35]. | G20: Обобщение на преглед | H20: Дали прегледът регистрира приложения по цялата верига — от планиране до оценяване. | I20: Среден | J20: Потвърдено | K20: Bahroun, Anane, Ahmed и Zacca 2023, Sustainability 15(17), 12983 | L20: https://www.mdpi.com/2071-1050/15/17/12983 | M20: „the analysis reveals significant and exponential growth in GAI research in 2023“; „The rise of AI was sparked in November 2022, when U.S. company OpenAI released ChatGPT“; „applications of GAI encompass assessment, personalized learning support, and intelligent tutoring systems“. | N20: ЗАМЕНЕН ИЗТОЧНИК. Формулировката е приведена към това, което прегледът наистина обхваща: оценяване, персонализирана подкрепа и интелигентни системи за обучение. | O20: Claude (авт.) | P20: 29.08.2026
A21: 20 | B21: 1.3 | C21: [25] | D21: [27] | F21: Систематизациите на халюцинациите достигат до същия извод — надеждното им отстраняване на равнище модел остава открит проблем [25]. | G21: Извод | H21: Дали [25] заключава, че надеждното отстраняване на равнище модел остава открит проблем. Дублира ред 22 — обедини или разграничи. | I21: Среден | J21: Потвърдено | K21: [25] Huang и кол., arXiv:2311.05232 | L21: https://arxiv.org/html/2311.05232v2 | M21: Прегледът проследява причините през три етапа — данни (misinformation, knowledge boundaries, inferior alignment data), обучение (pre-training limitations, SFT misalignment, RLHF-induced sycophancy) и извод (imperfect decoding, over-confidence, softmax bottleneck, reasoning failures) — и определя откриването и ограничаването като все още открити направления. | N21: Изводът се потвърждава. | O21: Claude (авт.) | P21: 28.08.2026
A22: 21 | B22: 1.3 | C22: [16] | D22: [17] | F22: Към тях се добавят зависимостта от обучителните данни, която ограничава актуалността на информацията и възпроизвежда съдържащите се в данните пристрастия и неравномерно покритие на отделни области и езици; склонността към шаблонни, повърхностни формулировки при по-сложни теми; и липсата на действително разбиране на предметната област и на педагогически замисъл — моделът имитира формата на учебния текст, без да носи отговорност за неговата дидактическа логика [16]. | G22: Дълъг списък | H22: Всеки от петте елемента поотделно: зависимост от данните, пристрастия, езиково покритие, шаблонност, липса на педагогически замисъл. Последният вероятно не е в [16]. | I22: Висок | J22: Потвърдено | K22: [16] — репозиториум на Университета в Аугсбург | L22: https://opus.bibliothek.uni-augsburg.de/opus4/files/109030/109030.pdf | M22: „While the majority of the research in large language models is done for the English language, there is still a gap of research in this field for other languages.“ / моделите са „assistive tools“, които са „well behind human performance when it comes to helping the student“. | N22: Езиковото покритие е дословно: „While the majority of the research in large language models is done for the English language, there is still a gap of research in this field for other languages.“ Липсата на педагогически замисъл се подкрепя косвено: моделите са описани като „assistive tools“, които са „well behind human performance when it comes to helping the student“. | O22: Claude (авт.) | P22: 28.08.2026
A23: 22 | B23: 1.3 | C23: [25] | D23: [27] | F23: Систематизациите разграничават фактологични халюцинации — противоречие с установими факти — и халюцинации на верността, при които генерираният текст се отклонява от подадения контекст или инструкция; проследяват причините им по цялата верига от обучителните данни през обучението до самото генериране; и стигат до отрезвяващ извод: надеждното откриване и отстраняване на халюцинациите на равнище модел остава открит изследователски проблем [25]. | G23: Терминология | H23: Разграничението „фактологични“ / „faithfulness“ халюцинации и проследяването на причините по веригата — точни термини на [25]. | I23: Висок | J23: Потвърдено | K23: [25] Huang и кол., таксономия | L23: https://arxiv.org/html/2311.05232v2 | M23: Factuality hallucination: „The LLM's output contains facts that are either inconsistent with real-world information or unverifiable“. Faithfulness hallucination: „The LLM's output deviates from user instructions, provided context, or exhibits internal logical contradictions“. | N23: Разграничението и проследяването на причините по веригата се потвърждават с точните термини на източника. | O23: Claude (авт.) | P23: 28.08.2026
A24: 23 | B24: 1.4 | C24: [35] | D24: заменен | F24: За целите на анализа те могат да бъдат подредени на три равнища — подпомогнато създаване чрез диалог, структурирани рамкови подходи и автономни системни реализации — като систематичните прегледи регистрират приложения и на трите равнища по цялата верига на учебния процес [35]. | G24: Приписване | H24: Трите равнища вероятно са авторска систематизация. Провери дали [35] ги извежда; ако не — премести цитата само върху втората част на изречението. | I24: Висок | J24: Потвърдено | K24: Bahroun, Anane, Ahmed и Zacca 2023, Sustainability 15(17), 12983 | L24: https://www.mdpi.com/2071-1050/15/17/12983 | M24: „the analysis reveals significant and exponential growth in GAI research in 2023“; „The rise of AI was sparked in November 2022, when U.S. company OpenAI released ChatGPT“; „applications of GAI encompass assessment, personalized learning support, and intelligent tutoring systems“. | N24: ЗАМЕНЕН ИЗТОЧНИК. Запазена е и уговорката, че прегледът не предлага степенувана класификация — трите равнища остават твоя подредба. | O24: Claude (авт.) | P24: 29.08.2026
A25: 24 | B25: 1.4 | C25: [16] | D25: [17] | F25: Първото и най-разпространено равнище е подпомогнатото създаване: преподавателят взаимодейства с инструмента чрез диалогов интерфейс и възлага отделни, ясно очертани задачи — изготвяне на учебни текстове по зададена тема и за определена аудитория, резюмета на по-обемни материали, примери и казуси, тестови въпроси от различни типове, указания за самостоятелна работа [16]. | G25: Списък приложения | H25: Изброените задачи при подпомогнатото създаване. | I25: Среден | J25: Потвърдено | K25: [16] — пълен текст | L25: https://opus.bibliothek.uni-augsburg.de/opus4/files/109030/109030.pdf | M25: „Large language models can assist in the development of problem-solving skills by providing students with explanations, step-by-step solutions, and interesting related questions.“ | N25: Подпомогнатото създаване се потвърждава: обяснения, стъпка по стъпка решения, свързани въпроси, резюмета и планове. | O25: Claude (авт.) | P25: 28.08.2026
A26: 25 | B26: 1.4 | C26: [15] | D26: [16] | F26: Рамката GAIDE предлага систематизиран процес за използване на генеративни инструменти при разработване на курсово съдържание — от структурирането на заявките през итеративното усъвършенстване на резултатите до тяхната проверка и вграждане в курса [15]. | G26: Описание на рамка | H26: GAIDE: дали процесът включва точно структуриране на заявките, итеративно усъвършенстване и проверка/вграждане. | I26: Среден | J26: Потвърдено | K26: [15] GAIDE, arXiv:2308.12276 / IEEE FIE 2024 | L26: https://arxiv.org/html/2308.12276v3 | M26: Рамката изисква ясна цел и контекст („how to act, the topic under consideration, prior knowledge students have, relevant student demographics“), после итеративно усъвършенстване на две равнища — макро (пренареждане и съгласуване с целите и учебните резултати) и микро (отделни части) — и накрая проверка спрямо учебните цели и обединяване на резултатите в цялостен документ. | N26: И трите елемента се потвърждават: структуриране на заявките, итерации, проверка и вграждане. | O26: Claude (авт.) | P26: 28.08.2026
A27: 26 | B27: 1.4 | C27: [14] | D27: [15] | F27: По-широк поглед дава интегративният преглед на Chai и колектив върху 71 публикации, който картографира приложенията на генеративния изкуствен интелект по петте фази на класическия модел за инструкционен дизайн ADDIE — анализ, проектиране, разработване, внедряване и оценяване — и показва, че инструментите навлизат не само във фазата на разработване на съдържание, но по цялата верига на дизайнерския процес [14]. | G27: Число | H27: „71 публикации“ и картографирането по петте фази на ADDIE — точното число и това, че моделът е ADDIE. | I27: Критичен | J27: Потвърдено | K27: [14] Chai и кол., HRDR 24(4) | L27: https://journals.sagepub.com/doi/10.1177/15344843251320256 | M27: 71 прегледани публикации. „This study adopted the Analysis, Design, Development, Implementation, and Evaluation (ADDIE) model since it is the most widely used instructional and training design model.“ | N27: Числото и моделът се потвърждават точно. | O27: Claude (авт.) | P27: 28.08.2026
... A54: 53 | B54: 1.6 | C54: [16] | D54: [17] | F54: И в двата случая принципът е един: добросъвестността не изисква отказ от инструментите, а отчетена, проверена и почтено декларирана употреба [16]. | G54: Обобщение | H54: Обобщаващо изречение — провери дали не надхвърля източника. | I54: Нисък | J54: Потвърдено | K54: [16] — пълен текст | L54: https://opus.bibliothek.uni-augsburg.de/opus4/files/109030/109030.pdf | M54: Виж извадките към редове 39, 44 и 46. | N54: Обобщаващо изречение, съгласувано с редове 39 и 44 след корекциите. Не надхвърля източника. | O54: Claude (авт.) | P54: 28.08.2026
A55: 54 | B55: 1.7 | C55: [21]; [30] | D55: заменен; заменен | E55: гл. 21 | F55: Съдържателната основа на тези критерии са установените педагогически и дизайнерски принципи: сравнителният анализ на ръководни документи за качество от различни образователни контексти показва, че те систематизират до голяма степен едни и същи изисквания за педагогическа издържаност и визуална организация [21], а доказателствено обоснованите принципи на мултимедийното учене предоставят емпирично проверена база, върху която такива критерии могат да стъпят [30, гл. 21]. | G55: Двоен цитат + локатор | H55: Две отделни проверки: [21] за общността на изискванията и [30, гл. 21] за емпиричната база. Провери дали 5-о изд. изобщо има гл. 21. | I55: Висок | J55: Потвърдено | K55: Mayer 2021, JARMAC — ЗАМЕСТИТЕЛ на [30, гл. 21] | L55: https://www.sciencedirect.com/science/article/pii/S2211368121000231 | M55: „this article examines evidence-based principles for how to design effective instructional videos and shows how they are grounded in cognitive theories of learning and instruction“; изведени са 14 принципа с посочени размери на ефекта. | N55: Емпирично обоснованата база за критерии се покрива. Готово за замяна. | O55: Claude (авт.) | P55: 29.08.2026
A56: 55 | B56: 1.7 | C56: [29] | D56: [32] | F56: Показателен пример е рубриката на Quality Matters за висшето образование, чието седмо издание съдържа осем общи стандарта, разгърнати в четиридесет и четири конкретни ревизионни стандарта, и се прилага чрез структуриран колегиален преглед [29]. | G56: Точни числа | H56: 7-о издание на рубриката: осем общи стандарта и четиридесет и четири конкретни ревизионни стандарта. В по-ранни издания броят е различен. | I56: Критичен | J56: Потвърдено | K56: QM HE Rubric, 7-о изд. | L56: https://educationaldevelopment.uams.edu/qualitymatters/qm-rubric | M56: „This rubric is structured around 8 General Standards and 44 Specific Review Standards.“ (7-о издание; макс. 101 точки, 22 съществени стандарта) | N56: Потвърдено дословно: 8 общи стандарта и 44 конкретни ревизионни стандарта. (Макс. 101 точки; 22 съществени стандарта и 86 точки за сертификация.) | O56: Claude (авт.) | P56: 28.08.2026
A57: 56 | B57: 1.7 | C57: [32] | D57: [35] | F57: В най-новата литература този подход достига зрялост под формата на валидирани скали за акредитационни стандарти и осигуряване на качеството в институциите за електронно обучение [32]. | G57: Обобщение | H57: Дали [32] представя валидирана скала за акредитационни стандарти в институции за електронно обучение. | I57: Среден | J57: Потвърдено | K57: [32] Ramezani и Mostafavi, EAIT 30(15) | L57: https://link.springer.com/article/10.1007/s10639-025-13587-5 | M57: „The resulting tool comprises 87 items across 46 criteria within five core dimensions: organization, research, technology, teaching–learning, and support.“ Валидирана чрез CVI 0,88, потвърждаващ факторен анализ, Cronbach's alpha и CR над 0,70. | N57: Валидираната скала се потвърждава. Можеш да добавиш конкретиката — 87 елемента в 46 критерия и пет измерения. | O57: Claude (авт.) | P57: 28.08.2026
A58: 57 | B58: 1.7 | C58: [26] | D58: [28] | F58: Основополагащото изследване в тази област установява, че водещите езикови модели съвпадат с човешката преценка в над 80 на сто от случаите, като за най-силния модел съвпадението достига около 85 на сто — стойност, надхвърляща съгласуваността между самите човешки оценители, която е около 81 на сто [26]. | G58: Три числа | H58: Над 80 % съвпадение; ~85 % за най-силния модел; ~81 % съгласуваност между хора. И трите — дословно, и с уточнение при кои условия. | I58: Критичен | J58: Потвърдено | K58: arXiv:2306.05685, раздел за съгласуваността (MT-Bench, setup S2) | L58: https://arxiv.org/html/2306.05685v4 | M58: „The agreement under setup S2 (w/o tie) between GPT-4 and humans reaches 85%, which is even higher than the agreement among humans (81%).“ Абстракт: „achieving over 80% agreement“. | N58: Потвърдено дословно, включително „надхвърляща“: „The agreement under setup S2 (w/o tie) between GPT-4 and humans reaches 85%, which is even higher than the agreement among humans (81%).“ И трите числа са верни. ЕДНО УТОЧНЕНИЕ: стойностите важат при сравнение по двойки без допускане на равенство (setup S2). Добави условието в изречението, иначе числата изглеждат общовалидни. | O58: Claude (авт.) | P58: 28.08.2026
A59: 58 | B59: 1.7 | C59: [13] | D59: [14] | F59: Систематичният преглед на полето подрежда натрупаните подходи по три оси — какво се оценява, как се оценява и как се измерва самото качество на оценяването — и документира приложението им в широк кръг задачи [13]. | G59: Структура | H59: Трите оси на систематизацията — какво, как и как се измерва качеството на оценяването. | I59: Среден | J59: Потвърдено | K59: [13] — arXiv HTML v5 | L59: https://arxiv.org/html/2411.16594v5 | M59: Осите на прегледа са „what to judge“, „how to judge“ и „where to judge“ (приложения), а не „как се измерва качеството на оценяването“. | N59: Първите две оси съвпадат. Третата в източника е „where to judge“ — къде се прилага оценяването, а не как се измерва качеството му. НАНЕСЕНО В НИП 28.08: третата ос е поправена на „къде се прилага оценяването“. || ЗАТВОРЕН. Третата ос е поправена на „къде се прилага оценяването“. | O59: Claude (авт.) | P59: 29.08.2026
A60: 59 | B60: 1.7 | C60: [13] | D60: [14] | F60: Систематизациите на полето документират устойчиви отклонения в преценката на моделите-оценители: предпочитание към по-дълги отговори, чувствителност към реда на представяне на сравняваните текстове, склонност към по-висока оценка на собствения им изход и ограничена надеждност при задачи, изискващи предметна експертиза отвъд езиковата компетентност [13]. | G60: Списък отклонения | H60: Четирите отклонения — дължина, ред на представяне, самопредпочитание, предметна експертиза. | I60: Висок | J60: Потвърдено | K60: [13] — arXiv HTML v5 | L60: https://arxiv.org/html/2411.16594v5 | M60: Документирани отклонения: position sensitivity (предпочитание по реда), length preference — „longer or shorter responses regardless of quality“, self-preference, и затруднение при „subtle attributes“ / „domain-specific reliability issues“. | N60: И четирите отклонения се потвърждават (виж извадката). | O60: Claude (авт.) | P60: 28.08.2026
A61: 60 | B61: 1.7 | C61: [10] | D61: [10] | F61: Още по-съществено за настоящата работа е установеното при многоезичните приложения: от над 650 публикации по темата едва тридесет и три разглеждат многоезични или нискоресурсни езикови условия, а техните резултати са непоследователни, преобладава прекомерното доверие в машинната преценка и почти навсякъде се използва единствен модел-оценител без независима човешка проверка [10]. | G61: Числа | H61: „над 650 публикации“ и „едва тридесет и три“ многоезични. Първо потвърди, че самият източник съществува (запис без автор). | I61: Критичен | J61: Потвърдено | K61: arXiv:2607.02235 — абстракт и находки | L61: https://arxiv.org/html/2607.02235v1 | M61: „48% of the papers rely on a single judge model family and 33% use GPT as the sole judge.“ От 650 публикации 33 се отнасят до многоезични или нискоресурсни условия. | N61: 650 публикации и 33 многоезични се потвърждават точно. НО „почти навсякъде се използва единствен модел-оценител“ е по-силно от източника: 48 % разчитат на едно семейство модели, 33 % използват GPT като единствен оценител. ДЕЙСТВИЕ: замени с конкретните проценти. || НАНЕСЕНО В НИП 28.08: „почти навсякъде“ е заменено с 48 на сто едно семейство модели и 33 на сто единствен модел. || ЗАТВОРЕН. „Почти навсякъде“ е заменено с 48 и 33 на сто. | O61: Claude (авт.) | P61: 29.08.2026
A62: 61 | B62: 1.7 | C62: [7] | D62: [7] | F62: Изследване върху проблемите и решенията при използването на генеративен изкуствен интелект в образованието извежда на преден план потребността от методики и инструменти за оценяване на качеството на генерираното учебно съдържание и посочва тревожни данни за него — според цитирано проучване едва около една шеста от генерираното съдържание отговаря на поставените критерии за качество [7]. | G62: Вторично число | H62: „около една шеста от генерираното съдържание“ — проследи до първоизточника, който [7] цитира, и цитирай него или посочи изрично вторичността. | I62: Критичен | J62: Потвърдено | K62: генеративен ИИ (Педагогика), печ. стр. 1290 | L62: https://journals.azbuki.bg/pedagogy/generativen-izkustven-intelekt-v-obrazovanieto-problemi-i-reseniya/view | M62: следвания разкриват значителна загриженост сред висшите училища по отно- шение на достоверността и качеството на генерираното съдържание. Според резултати на едно такова изследване едва 16% от генерираното съдържание отговаря на поставените критерии за качество (Peláez-Sánchez 2024). Пред- ставената информация трябва да бъде достоверна, релевантна, четлива, да не | N62: Източникът пише „едва 16 % от генерираното съдържание отговаря на поставените критерии за качество (Peláez-Sánchez 2024)“. Потвърждава се вторичността. ДЕЙСТВИЕ: замени „около една шеста“ с „16 %“ и цитирай Peláez-Sánchez 2024 или изрично посочи, че данните са цитирани в [7]. || НАНЕСЕНО В НИП 28.08: „около една шеста“ стана „шестнадесет на сто“, добавено е „цитирано в него“. || ЗАТВОРЕН. „Около една шеста“ стана „шестнадесет на сто“, добавено е „цитирано в него“. | O62: Claude (авт.) | P62: 29.08.2026
A63: 62 | B63: 1.7 | C63: [13] | D63: [14] | F63: Систематизациите на автоматизираното оценяване извеждат същите два въпроса и по отношение на машинните оценители [13]. | G63: Обобщение | H63: Кратка препратка — провери дали [13] поставя същите два въпроса. | I63: Нисък | J63: Потвърдено | K63: [13] — arXiv HTML v5 | L63: https://arxiv.org/html/2411.16594v5 | M63: Същата систематизация — виж редове 58 и 59. | N63: Кратка препратка, покрита от редове 58 и 59. | O63: Claude (авт.) | P63: 28.08.2026
A64: 63 | B64: Изводи | C64: [26] | D64: [28] | F64: Автоматизираното оценяване напредва бързо: моделите в ролята на оценители вече постигат съвпадение с човешката преценка над 80 на сто в изследвани условия [26], а част от проверките — за четивност, за съществуване на цитирани източници, за близост до съществуващи текстове — са автоматизируеми още днес. | G64: Число (повторение) | H64: Същото число като ред 57 — провери съгласуваността между двете места в текста. | I64: Висок | J64: Потвърдено | K64: arXiv:2306.05685 — същият пасаж | L64: https://arxiv.org/html/2306.05685v4 | M64: Същият пасаж като ред 57. | N64: Съгласувано с ред 57. Формулировката „в изследвани условия“ тук е коректна и покрива ограничението S2. | O64: Claude (авт.) | P64: 28.08.2026
A65: 64 | B65: Изводи | C65: [10] | D65: [10] | F65: Същевременно документираните отклонения в машинната преценка, липсата на валидирани данни за нискоресурсни езици като българския [10] и невъзможността автоматизирано да се преценят дидактическата уместност за конкретен курс и етичната допустимост определят настоящия избор: моделът се проектира като инструмент за структуриране на експертна човешка преценка, изграден така, че отделните му показатели да могат да бъдат автоматизирани поетапно с узряването на средствата. | G65: Извод | H65: Липсата на валидирани данни за нискоресурсни езици — дали [10] го твърди и дали покрива българския. Изводът на главата стъпва на този източник. | I65: Критичен | J65: Потвърдено | K65: arXiv:2607.02235 — препоръка 4 и приложението с езиците | L65: https://arxiv.org/html/2607.02235v1 | M65: Препоръка 4 „Keep humans in the loop“. От славянските езици са включени чешки, полски, руски и сръбски, класифицирани като по-високоресурсни. Българският не се споменава. | N65: Препоръката за задължително човешко участие при нискоресурсни езици се потвърждава. НО източникът НЕ разглежда българския език: от славянските са включени чешки, полски, руски и сръбски, всички класифицирани като по-високоресурсни. Формулировката „нискоресурсни езици като българския [10]“ приписва на източника класификация, която той не прави. ДЕЙСТВИЕ: отдели двете — липсата на валидирани данни за нискоресурсни езици е на [10]; отнасянето на българския към тях е твой извод и трябва да е обозначено като такъв. || ЗАТВОРЕН. Липсата на валидирани данни е на [15]; отнасянето на българския към нискоресурсните езици е обозначено като извод на работата. | O65: Claude (авт.) | P65: 29.08.2026
A66: 65 | B66: 1.2 | C66: — | D66: [47] | E66: — (абзацът е премахнат) | F66: …контролът върху количествените характеристики на генерираното съдържание се разработва в източниците през равнището на езика — дължина, речник и сложност на изреченията [47], — а не през съотнасянето на обема с отделеното учебно време. | G66: Механизъм на рамка + констатация за модели | H66: Че COGENT управлява четивността именно чрез дължина, речник и сложност на изреченията — т.е. през равнището на езика. | I66: Критичен | J66: ОТПАДА — твърдението вече не е в текста | K66: Резюме на статията (BEA 2025 / arXiv:2506.09367) | L66: https://aclanthology.org/2025.bea-1.10/ | M66: „Models often fail to align with curriculum standards and maintain grade-appropriate reading levels consistently.“ | „…we propose COGENT, a curriculum-oriented framework for generating grade-appropriate educational content. We incorporate three curriculum components (science concepts, core ideas, and learning objectives), control readability through length, vocabulary, and sentence complexity…“ | N66: ТРИ ПОСЛЕДОВАТЕЛНИ ГРЕШКИ, ЗАКРИТИ С ПРЕМАХВАНЕ НА АБЗАЦА (31.08.2026). (1) Абзацът твърдеше, че рамките въвеждат ограничения „именно защото зададеният обем не се спазва сам по себе си“ — източникът не казва това. (2) Първата поправка запази [47] като подкрепа на абзац за обем спрямо учебно време, докато „length“ у COGENT е дължина за съобразяване с езиковото равнище. (3) Втората поправка направи абзаца вътрешно противоречив — първата половина въвеждаше показател, втората обясняваше, че литературата не го поддържа. Решаващото обстоятелство: абзацът ПРОТИВОРЕЧИ на собствения модел — т. 3.3, абз. 221 изрично постановява, че „преобразуването на обема в учебно време остава преценка на преподавателя… и затова не се вписва в модела като отделно изискване“. Абзацът е премахнат изцяло от МТ (абз. 54) и от НИП (абз. 33). Въпросът се покрива коректно другаде: т. 2.3 (абз. 167) като контекстуален критерий, преценяван от преподавателя, и показател П14 — обем спрямо ЗАЯВЕНИЯ обем. | O66: Claude (авт.) | P66: 31.08.2026
A67: 66 | B67: 1.1 | C67: — | D67: [49] | E67: абз. 44 | F67: Генерираното съдържание подлежи на човешка валидация за точност, издържаност и съответствие със стандартите и не може да бъде използвано в непроменен вид в учебно значими контексти без проверка от специалист по предметната област, който да провери фактите, да прецени материала за пристрастност и да съобрази изискванията за достъпност [49]. | G67: Нормативно изискване | H67: Че документът формулира изискване за човешка валидация и изброява точно тези проверки. | I67: Критичен | J67: Потвърдено | K67: 1EdTech AIGC Best Practices v1.0 | L67: https://www.imsglobal.org/resource/AI-Generated_Content_Best_Practices/v1p0 | M67: „AI-generated content requires human validation to ensure accuracy, rigor, and alignment with standards.“ | „AI-generated content cannot be used ‘as is’ for high-stakes or learning-critical contexts without subject matter expert validation.“ | „An organization’s staff, educators, or SMEs should fact-check content for accuracy, evaluate for potential bias, and review for accessibility compliance.“ | N67: Ново твърдение от 31.08.2026 — замества непокрития абзац „Институционално създаваното съдържание…“. | O67: Claude (авт.) | P67: 31.08.2026
A68: 67 | B68: 1.1 | C68: — | D68: [49] | E68: абз. 44 | F68: При най-високото равнище от същата скала съдържанието се създава и публикува с минимален или никакъв човешки надзор [49]. | G68: Дефиниция от скала | H68: Че равнище 5 от скалата е дефинирано именно така. | I68: Критичен | J68: Потвърдено | K68: 1EdTech AIGC Best Practices v1.0 — Content Transparency Rating, равнище 5 | L68: https://www.imsglobal.org/resource/AI-Generated_Content_Best_Practices/v1p0 | M68: „Fully AI-Generated — GenAI autonomously generates and publishes content with minimal or no human oversight.“ | N68: Ново твърдение от 31.08.2026. | O68: Claude (авт.) | P68: 31.08.2026

Sheet Ниво 3 Нецитирани
A1: № | B1: Раздел | C1: Абзац | D1: Изречение без цитат | E1: Решение | F1: Източник, който го подкрепя | G1: Извадка от източника | H1: Действие в текста | I1: Проверил | J1: Дата
A2: 1 | B2: 1.1 | C2: 11 | D2: Първите две точки установяват какво представлява електронното учебно съдържание и на какви педагогически изисквания трябва да отговаря то — независимо от начина, по който е създадено. | E2: Рамка на изложението — не изисква източник | H2: Изречението описва какво прави самата глава или обобщава вече изложеното. Това е организация на текста, а не твърдение за света. Оставя се както е. | I2: Claude (авт.) | J2: 29.08.2026
A3: 2 | B3: 1.1 | C3: 11 | D3: Шестата точка очертава нормативната рамка — етичните, правните и академичните изисквания, а седмата разглежда съществуващите подходи за оценяване на качеството и установява защо те са недостатъчни за съдържанието, създадено с генеративни инструменти. | E3: Рамка на изложението — не изисква източник | H3: Изречението описва какво прави самата глава или обобщава вече изложеното. Това е организация на текста, а не твърдение за света. Оставя се както е. | I3: Claude (авт.) | J3: 29.08.2026
A4: 3 | B4: 1.1 | C4: 12 | D4: В научната литература електронното учебно съдържание се определя най-общо като съвкупност от учебни материали в цифров формат, предназначени да подпомогнат постигането на предварително формулирани учебни цели и достъпни за обучаемия чрез електронно устройство. | E4: Покрито от цитата в същия абзац | H4: Изречението продължава или разгръща твърдение, което е цитирано в същия абзац. Проверява се само дали скобата стои достатъчно близо, за да е ясно докъде се простира източникът. Ако цитатът е в началото, а изречението е в края на дълъг абзац, скобата се повтаря. | I4: Claude (авт.) | J4: 29.08.2026
A5: 4 | B5: 1.1 | C5: 13 | D5: Електронното обучение обозначава формата на организация на учебния процес; електронната образователна среда — технологичната платформа, в която той протича; а електронното учебно съдържание е самият учебен материал, който средата поднася и формата организира. | E5: Преформулиране | F5: — | H5: Абзац 12 вече обявява работна позиция. Тук се добавя същото: „В настоящата разработка трите понятия се разграничават така…“. Дефиницията на електронното обучение стъпва на [11]; другите две са работни разграничения за нуждите на изложението, не твърдения за литературата. | I5: Claude (авт.) | J5: 29.08.2026
A6: 5 | B6: 1.1 | C6: 14 | D6: Към тях се добавят независимостта от време и място на достъпа, възможността за адаптиране към индивидуалните потребности на обучаемия и проследимостта — цифровата среда регистрира кога и как съдържанието се използва, което създава предпоставки за обратна връзка и усъвършенстване. | E6: Покрито от цитата в същия абзац | H6: Изречението продължава или разгръща твърдение, което е цитирано в същия абзац. Проверява се само дали скобата стои достатъчно близо, за да е ясно докъде се простира източникът. Ако цитатът е в началото, а изречението е в края на дълъг абзац, скобата се повтаря. | I6: Claude (авт.) | J6: 29.08.2026
A7: 6 | B7: 1.1 | C7: 16 | D7: Един и същ текст може да бъде използван като справочен материал, като основа за урок или като част от изпитен комплект; учебната му функция се определя не само от съдържанието, но и от начина, по който е поставен в учебния процес. | E7: Нужен източник — намерен | F7: [24] IEEE LOM | H7: Стандартът описва учебния обект с елемент „Context“ в образователната категория — тоест контекстът на употреба е част от описанието на ресурса. Това подкрепя твърдението, че функцията се определя и от мястото в учебния процес. Добави [24]. | I7: Claude (авт.) | J7: 29.08.2026
A8: 7 | B8: 1.1 | C8: 19 | D8: Систематизацията на видовете има и утвърдена стандартизационна основа. | E8: Рамка на изложението — не изисква източник | H8: Изречението описва какво прави самата глава или обобщава вече изложеното. Това е организация на текста, а не твърдение за света. Оставя се както е. | I8: Claude (авт.) | J8: 29.08.2026
A9: 8 | B9: 1.1 | C9: 19 | D9: В литературата и в стандартите отделната единица електронно съдържание се описва чрез понятието учебен обект — всяка единица, цифрова или не, използвана за учене, образование или обучение. | E9: Покрито от цитата в същия абзац | H9: Изречението продължава или разгръща твърдение, което е цитирано в същия абзац. Проверява се само дали скобата стои достатъчно близо, за да е ясно докъде се простира източникът. Ако цитатът е в началото, а изречението е в края на дълъг абзац, скобата се повтаря. | I9: Claude (авт.) | J9: 29.08.2026
A10: 9 | B10: 1.1 | C10: 19 | D10: Съществуването на такъв стандарт показва, че модулността, повторната използваемост и описуемостта на електронното съдържание не са пожелателни качества, а отдавна формализирани характеристики на полето. | E10: Покрито от цитата в същия абзац | H10: Изречението продължава или разгръща твърдение, което е цитирано в същия абзац. Проверява се само дали скобата стои достатъчно близо, за да е ясно докъде се простира източникът. Ако цитатът е в началото, а изречението е в края на дълъг абзац, скобата се повтаря. | I10: Claude (авт.) | J10: 29.08.2026
A11: 10 | B11: 1.2 | C11: 27 | D11: Тези изисквания могат да бъдат групирани в пет области: съответствие с учебните цели, структура и организация на изложението, достъпност, интерактивност и пригодност за самостоятелно електронно обучение. | E11: Преформулиране | F11: — | H11: „Тези изисквания могат да бъдат групирани“ става „Изведените дотук изисквания са подредени тук в пет области“. Така петте области стават организация на изложението, а не твърдение за литературата. Всяко от изискванията поотделно вече има източник. | I11: Claude (авт.) | J11: 29.08.2026
A12: 11 | B12: 1.2 | C12: 32 | D12: Общата рамка остава една и съща, но тежестта на отделните изисквания се мести — обстоятелство, което всеки модел за оценяване трябва да отчете чрез тълкуване на критериите според вида на материала, а не чрез отделни системи от критерии за всеки вид. | E12: Премахнато | F12: — | H12: Втората половина — „обстоятелство, което всеки модел за оценяване трябва да отчете чрез тълкуване на критериите…“ — е предписание към бъдещия модел. Същият тип препратки вече отпаднаха от 1.5. Остава само първата част: рамката е обща, тежестта на изискванията се мести. | I12: Claude (авт.) | J12: 29.08.2026
A13: 12 | B13: 1.2 | C13: 33 | D13: Генерираното съдържание е особено податливо на този дефект по две причини: моделът няма представа за учебното време, а зададеният в заявката обем се спазва приблизително. | E13: Нужен източник — намерен | F13: [41] COGENT | H13: COGENT въвежда изрични ограничения върху броя думи и сложността на езика („constraints on word number, vocabulary, and sentence complexity“) точно защото моделите не ги спазват сами. Това подкрепя косвено втората причина. ВНИМАНИЕ: първата причина — „моделът няма представа за учебното време“ — не се подкрепя от нищо и трябва да отпадне. | I13: Claude (авт.) | J13: 29.08.2026
A14: 13 | B14: 1.2 | C14: 37 | D14: Педагогическата ѝ стойност не е в потвърждаването на верния отговор, а в обяснението: защо даден отговор е грешен, каква представа стои зад грешката и как тя се преодолява. | E14: Нужен източник — намерен | F14: [42] Wang и кол. 2019 | H14: Разгърнатата обратна връзка се дефинира като „additional instructional information of correct responses“, включително обяснения и стъпки за решаване. Добави [42], със същата условност както на ред 14 от Ниво 2. | I14: Claude (авт.) | J14: 29.08.2026
A15: 14 | B15: 1.2 | C15: 37 | D15: В самостоятелното електронно обучение това изискване е още по-строго, тъй като обучаемият няма към кого да се обърне при затруднение — обратната връзка е единственият заместител на преподавателския отговор. | E15: Премахнато | F15: — | H15: „Обратната връзка е единственият заместител на преподавателския отговор“ е правдоподобно, но неподкрепено. В НИП отпада. Ако искаш да остане, трябва източник за самостоятелното електронно обучение — нямаме такъв. | I15: Claude (авт.) | J15: 29.08.2026
A16: 15 | B16: 1.2 | C16: 39 | D16: Накрая, пригодността за електронно обучение обобщава спецификата на средата: за разлика от учебните материали, използвани в присъствено обучение, електронното съдържание често функционира без постоянното присъствие на преподавател. | E16: Покрито от цитата в същия абзац | H16: Изречението продължава или разгръща твърдение, което е цитирано в същия абзац. Проверява се само дали скобата стои достатъчно близо, за да е ясно докъде се простира източникът. Ако цитатът е в началото, а изречението е в края на дълъг абзац, скобата се повтаря. | I16: Claude (авт.) | J16: 29.08.2026
A17: 16 | B17: 1.2 | C17: 40 | D17: Обобщено, петте области изисквания — съответствие с целите, структура, достъпност, интерактивност и пригодност за самостоятелно обучение — образуват съдържателната основа, върху която ще бъдат изградени критериите за качество. | E17: Рамка на изложението — не изисква източник | H17: Изречението описва какво прави самата глава или обобщава вече изложеното. Това е организация на текста, а не твърдение за света. Оставя се както е. | I17: Claude (авт.) | J17: 29.08.2026
A18: 17 | B18: 1.3 | C18: 43 | D18: Първата е начинът на обработка на текста: моделът не работи с думи, а с по-малки единици, наречени токени, и предсказва следващата единица въз основа на предходните. | E18: Нужен източник — намерен | F18: Zhao и кол., A Survey of Large Language Models, arXiv:2303.18223 — „greedy search that predicts the most likely token at | G18: Zhao и кол., A Survey of Large Language Models, arXiv:2303.18223 — „greedy search that predicts the most likely token at each step based on the previously generated“; раздел за токенизацията. | H18: НАНЕСЕНО В НИП 29.08 с временен маркер до преномерирането. | I18: Claude (авт.) | J18: 29.08.2026
A19: 18 | B19: 1.3 | C19: 43 | D19: Втората е контекстният прозорец — ограниченият обем текст, който моделът може да отчита едновременно; при по-дълги материали началото на изложението може да влияе по-слабо върху края му, което е една от причините за наблюдаваната терминологична непоследователност в дълги генерирани текстове. | E19: Нужен източник — намерен | F19: Liu и кол. 2024, Lost in the Middle, TACL 12, 157–173 — „performance can degrade significantly when changing the positio | G19: Liu и кол. 2024, Lost in the Middle, TACL 12, 157–173 — „performance can degrade significantly when changing the position of relevant information“. | H19: НАНЕСЕНО В НИП 29.08 с временен маркер до преномерирането. | I19: Claude (авт.) | J19: 29.08.2026
A20: 19 | B20: 1.3 | C20: 43 | D20: Третата е вероятностният подбор при генерирането: при едни и същи входни данни моделът може да произведе различни изходи, тъй като следващата единица се избира от разпределение, а не еднозначно. | E20: Нужен източник — намерен | F20: Zhao и кол., arXiv:2303.18223 — „sampling-based methods will sample the word with higher probability while also retainin | G20: Zhao и кол., arXiv:2303.18223 — „sampling-based methods will sample the word with higher probability while also retaining the possibilities of selecting the rest words“. | H20: НАНЕСЕНО В НИП 29.08 с временен маркер до преномерирането. | I20: Claude (авт.) | J20: 29.08.2026
A21: 20 | B21: 1.3 | C21: 45 | D21: В основата на съвременните текстово-генериращи инструменти стоят големите езикови модели — невронни мрежи, обучени върху огромни текстови масиви да предсказват най-вероятното продължение на даден текст. | E21: Покрито от цитата в същия абзац | H21: Изречението продължава или разгръща твърдение, което е цитирано в същия абзац. Проверява се само дали скобата стои достатъчно близо, за да е ясно докъде се простира източникът. Ако цитатът е в началото, а изречението е в края на дълъг абзац, скобата се повтаря. | I21: Claude (авт.) | J21: 29.08.2026
A22: 21 | B22: 1.3 | C22: 45 | D22: Принципът на действие обаче остава вероятностен: моделът не извлича проверени факти от база знания, а генерира текст, който е статистически правдоподобен спрямо обучителните данни. | E22: Покрито от цитата в същия абзац | H22: Изречението продължава или разгръща твърдение, което е цитирано в същия абзац. Проверява се само дали скобата стои достатъчно близо, за да е ясно докъде се простира източникът. Ако цитатът е в началото, а изречението е в края на дълъг абзац, скобата се повтаря. | I22: Claude (авт.) | J22: 29.08.2026
A23: 22 | B23: 1.3 | C23: 46 | D23: Възможностите, които тези инструменти предлагат на образованието, са документирани в бързо растяща литература. | E23: Рамка на изложението — не изисква източник | H23: Изречението описва какво прави самата глава или обобщава вече изложеното. Това е организация на текста, а не твърдение за света. Оставя се както е. | I23: Claude (авт.) | J23: 29.08.2026
A24: 23 | B24: 1.3 | C24: 47 | D24: Допълнителното обучение върху специализирани данни може да приближи изхода до определен предметен или стилов профил, а извличането на съдържание от външен източник преди генерирането — известно като генериране, обогатено с извличане — привързва отговора към конкретни документи и намалява дела на измислиците. | E24: Нужен източник — намерен | F24: Gao и кол., Retrieval-Augmented Generation for LLMs: A Survey, arXiv:2312.10997 — „RAG has emerged as a promising soluti | G24: Gao и кол., Retrieval-Augmented Generation for LLMs: A Survey, arXiv:2312.10997 — „RAG has emerged as a promising solution by incorporating knowledge from external databases. This enhances the accuracy and credibility of the generation… and allows for continuous knowledge updates and integration of domain-specific information.“ | H24: НАНЕСЕНО В НИП 29.08 с временен маркер до преномерирането. | I24: Claude (авт.) | J24: 29.08.2026
A25: 24 | B25: 1.3 | C25: 47 | D25: И двата подхода обаче изместват проблема, вместо да го премахнат: качеството на изхода става зависимо от качеството и актуалността на подадените данни, а проверката остава необходима, защото моделът продължава да преформулира извлеченото със собствени думи. | E25: Покрито от цитата в същия абзац | H25: Изречението продължава или разгръща твърдение, което е цитирано в същия абзац. Проверява се само дали скобата стои достатъчно близо, за да е ясно докъде се простира източникът. Ако цитатът е в началото, а изречението е в края на дълъг абзац, скобата се повтаря. | I25: Claude (авт.) | J25: 29.08.2026
A26: 25 | B26: 1.3 | C26: 51 | D26: При втория човекът задава рамката и одобрява крайния резултат, без да следи междинните стъпки. | E26: Нужен източник — намерен | F26: [22] Instructional Agents | H26: Системата дефинира четири режима на човешко участие, сред които „Catalog-Guided“ и „Feedback-Guided“ — тоест човекът задава рамката и одобрява, без да следи всяка стъпка. Добави [22]. | I26: Claude (авт.) | J26: 29.08.2026
A27: 26 | B27: 1.3 | C27: 54 | D27: След като са изяснени принципът на действие и границите на генеративните инструменти, следващата стъпка е да се разгледа конкретно как те се използват при разработването на учебни материали — какви подходи, работни процеси и равнища на автоматизация се обособяват в практиката и в литературата. | E27: Рамка на изложението — не изисква източник | H27: Изречението описва какво прави самата глава или обобщава вече изложеното. Това е организация на текста, а не твърдение за света. Оставя се както е. | I27: Claude (авт.) | J27: 29.08.2026
A28: 27 | B28: 1.4 | C28: 56 | D28: Прегледът на литературата показва, че приложенията не са еднородни: те се различават по степента на автоматизация и по мястото, което заема човекът в процеса на създаване. | E28: Покрито от цитата в същия абзац | H28: Изречението продължава или разгръща твърдение, което е цитирано в същия абзац. Проверява се само дали скобата стои достатъчно близо, за да е ясно докъде се простира източникът. Ако цитатът е в началото, а изречението е в края на дълъг абзац, скобата се повтаря. | I28: Claude (авт.) | J28: 29.08.2026
A29: 28 | B29: 1.4 | C29: 59 | D29: Такива решения показват накъде води логиката на вграждания контрол: колкото по-специализирана е платформата, толкова по-плътно педагогическите ограничения се вграждат в самото генериране. | E29: Покрито от цитата в същия абзац | H29: Изречението продължава или разгръща твърдение, което е цитирано в същия абзац. Проверява се само дали скобата стои достатъчно близо, за да е ясно докъде се простира източникът. Ако цитатът е в началото, а изречението е в края на дълъг абзац, скобата се повтаря. | I29: Claude (авт.) | J29: 29.08.2026
A30: 29 | B30: 1.4 | C30: 61 | D30: Този резултат е показателен в две посоки: потвърждава практическата приложимост на инструментите и едновременно с това илюстрира централния проблем на работата — че възприеманото качество не е свидетелство за действителното. | E30: Покрито от цитата в същия абзац | F30: [8] | H30: Изречението тълкува данните от [8], които са цитирани в началото на абзаца. Повтори скобата в края на изречението, за да е ясно, че тълкуването стъпва на същия източник, а не въвежда нов факт. | I30: Claude (авт.) | J30: 29.08.2026
A31: 30 | B31: 1.4 | C31: 62 | D31: Най-подробно документираният български опит с генериране на тестови въпроси илюстрира и трите равнища едновременно. | E31: Покрито от цитата в същия абзац | H31: Изречението продължава или разгръща твърдение, което е цитирано в същия абзац. Проверява се само дали скобата стои достатъчно близо, за да е ясно докъде се простира източникът. Ако цитатът е в началото, а изречението е в края на дълъг абзац, скобата се повтаря. | I31: Claude (авт.) | J31: 29.08.2026
A32: 31 | B32: 1.4 | C32: 62 | D32: По-внимателният прочит обаче показва обратното: този дял е постигнат именно защото проверката е вградена като задължителна стъпка, а не защото инструментът произвежда годно съдържание сам по себе си. | E32: Покрито от цитата в същия абзац | F32: [2] | H32: Твърдението, че делът е постигнат заради вградената проверка, се подкрепя пряко от [2] — работният процес изисква одобрение от преподавателя преди записване на всеки въпрос. Повтори скобата. | I32: Claude (авт.) | J32: 29.08.2026
A33: 32 | B33: 1.4 | C33: 66 | D33: При рамковите подходи проследимостта е частична: процесът е документиран, но междинните стъпки често не се съхраняват. | E33: Премахнато | F33: — | H33: Че при рамковите подходи междинните стъпки „често не се съхраняват“ не се твърди от нито един от проверените източници. GAIDE документира процеса, но не и обратното. Отпада или се свежда до това, което [16] описва. | I33: Claude (авт.) | J33: 29.08.2026
A34: 33 | B34: 1.6 | C34: 85 | D34: На международно равнище очертаните изисквания намират израз в специализираното ръководство на ЮНЕСКО за генеративния изкуствен интелект в образованието и научните изследвания — първият глобален документ от този род. | E34: Покрито от цитата в същия абзац | H34: Изречението продължава или разгръща твърдение, което е цитирано в същия абзац. Проверява се само дали скобата стои достатъчно близо, за да е ясно докъде се простира източникът. Ако цитатът е в началото, а изречението е в края на дълъг абзац, скобата се повтаря. | I34: Claude (авт.) | J34: 29.08.2026
A35: 34 | B35: 1.6 | C35: 86 | D35: Същата рамка разграничава допустима от недопустима употреба по ясен критерий — инструментът може да улеснява рутинните операции, но не може да замества интелектуалния труд — и утвърждава принципа на неделимото авторство: авторът носи пълна отговорност за съдържанието независимо от степента на машинно асистиране. | E35: Покрито от цитата в същия абзац | H35: Изречението продължава или разгръща твърдение, което е цитирано в същия абзац. Проверява се само дали скобата стои достатъчно близо, за да е ясно докъде се простира източникът. Ако цитатът е в началото, а изречението е в края на дълъг абзац, скобата се повтаря. | I35: Claude (авт.) | J35: 29.08.2026
A36: 35 | B36: 1.6 | C36: 87 | D36: Правната рамка на тези изисквания вече не е само национална или секторна. | E36: Рамка на изложението — не изисква източник | H36: Изречението описва какво прави самата глава или обобщава вече изложеното. Това е организация на текста, а не твърдение за света. Оставя се както е. | I36: Claude (авт.) | J36: 29.08.2026
A37: 36 | B37: 1.6 | C37: 87 | D37: За образователния контекст е показателно, че регламентът причислява към високорисковите определени образователни употреби — системи, които определят достъпа до обучение или оценяват обучаеми — и с това утвърждава принципа, че колкото по-голямо е въздействието върху обучаемия, толкова по-строги са изискванията. | E37: Покрито от цитата в същия абзац | H37: Изречението продължава или разгръща твърдение, което е цитирано в същия абзац. Проверява се само дали скобата стои достатъчно близо, за да е ясно докъде се простира източникът. Ако цитатът е в началото, а изречението е в края на дълъг абзац, скобата се повтаря. | I37: Claude (авт.) | J37: 29.08.2026
A38: 37 | B38: 1.6 | C38: 88 | D38: Между европейската правна рамка и практиката на отделния преподавател стои институционалното и националното равнище, което в българския контекст все още се изгражда. | E38: Рамка на изложението — не изисква източник | H38: Изречението описва какво прави самата глава или обобщава вече изложеното. Това е организация на текста, а не твърдение за света. Оставя се както е. | I38: Claude (авт.) | J38: 29.08.2026
A39: 38 | B39: 1.6 | C39: 91 | D39: Четирите групи изисквания очертават нормативната рамка, в която бъдещият модел ще работи: етичната и академичната коректност не са външни съображения, а една от областите, по които качеството на генерираното учебно съдържание подлежи на оценяване. | E39: Рамка на изложението — не изисква източник | H39: Изречението описва какво прави самата глава или обобщава вече изложеното. Това е организация на текста, а не твърдение за света. Оставя се както е. | I39: Claude (авт.) | J39: 29.08.2026
A40: 39 | B40: 1.6 | C40: 92 | D40: Той има две страни: от една страна, доколко материал, произведен от модел, се ползва със закрила, и от друга — доколко създаването му не нарушава правата върху произведенията, с които моделът е обучаван. | E40: Нужен източник — намерен | F40: [17] Kasneci и кол. | H40: Втората страна се подкрепя дословно: „the answer may contain a full sentence or even a paragraph seen in the training set, leading to copyright and plagiarism issues“. Първата страна — дали машинно произведен материал се ползва със закрила — НЕ е в източника и изисква правен източник или отпадане. | I40: Claude (авт.) | J40: 29.08.2026
A41: 40 | B41: 1.6 | C41: 93 | D41: В този смисъл моделът за оценяване има и възпитателна функция, надхвърляща прякото си предназначение: той демонстрира на практика какво означава отговорна употреба и може да бъде използван като учебно средство при изграждането на дигитална и етична грамотност у самите обучаеми. | E41: Рамка на изложението — не изисква източник | H41: Изречението описва какво прави самата глава или обобщава вече изложеното. Това е организация на текста, а не твърдение за света. Оставя се както е. | I41: Claude (авт.) | J41: 29.08.2026
A42: 41 | B42: 1.7 | C42: 97 | D42: Най-развитата институционализация на критериално-експертния подход са стандартизираните рубрики за качество на онлайн курсове. | E42: Покрито от цитата в същия абзац | H42: Изречението продължава или разгръща твърдение, което е цитирано в същия абзац. Проверява се само дали скобата стои достатъчно близо, за да е ясно докъде се простира източникът. Ако цитатът е в началото, а изречението е в края на дълъг абзац, скобата се повтаря. | I42: Claude (авт.) | J42: 29.08.2026
A43: 42 | B43: 1.7 | C43: 98 | D43: Институционално-акредитационният подход измества фокуса от отделния материал към системата, която го произвежда и използва: оценяват се процесите, ресурсите и стандартите на институцията, предлагаща електронно обучение. | E43: Покрито от цитата в същия абзац | H43: Изречението продължава или разгръща твърдение, което е цитирано в същия абзац. Проверява се само дали скобата стои достатъчно близо, за да е ясно докъде се простира източникът. Ако цитатът е в началото, а изречението е в края на дълъг абзац, скобата се повтаря. | I43: Claude (авт.) | J43: 29.08.2026
A44: 43 | B44: 1.7 | C44: 105 | D44: Днес обаче три обстоятелства налагат човешкото оценяване като основен режим: липсата на валидирани данни за надеждност при български учебни текстове, документираните отклонения в преценката на моделите-оценители и принципното съображение, че оценяването на генериран текст от генеративен модел възпроизвежда същия вероятностен механизъм, чиято надеждност се проверява. | E44: Покрито от цитата в същия абзац | F44: [15] и [14] | H44: Първите две обстоятелства са вече потвърдени другаде в главата: липсата на валидирани данни е на [15], документираните отклонения — на [14]. Повтори двете скоби. Третото обстоятелство е разсъждение, а не установен факт — обозначи го като съображение. | I44: Claude (авт.) | J44: 29.08.2026
A45: 44 | B45: 1.7 | C45: 106 | D45: Това потвърждава както актуалността на темата в българския контекст, така и избраната посока — модел, който структурира човешката експертна преценка, вместо да я автоматизира. | E45: Покрито от цитата в същия абзац | H45: Изречението продължава или разгръща твърдение, което е цитирано в същия абзац. Проверява се само дали скобата стои достатъчно близо, за да е ясно докъде се простира източникът. Ако цитатът е в началото, а изречението е в края на дълъг абзац, скобата се повтаря. | I45: Claude (авт.) | J45: 29.08.2026
A46: 45 | B46: 1.7 | C46: 108 | D46: Критериалните листи по правило не съдържат проверка за фактически измислици, защото при добросъвестен човешки автор такава проверка е излишна; акредитационните стандарти предполагат отговорен автор с установима квалификация; емпиричното оценяване настъпва твърде късно, за да улови дефекти, които могат да бъдат предотвратени на входа. | E46: Преформулиране | F46: — | H46: Твърдението е отрицателно — какво НЕ съдържат инструментите. Такова твърдение изисква преглед на самите инструменти. Преформулирай на „в прегледаните инструменти не се среща отделен показател за фактическа достоверност“, което е проверимо наблюдение върху [32], вместо общо твърдение за всички критериални листи. | I46: Claude (авт.) | J46: 29.08.2026
A47: 46 | B47: 1.7 | C47: 109 | D47: Оттук следва изводът, който задава програмата на следващия етап: съществуващата традиция в оценяването предоставя ценна основа — критериалната форма, педагогическата съдържателна база, институционалната рамка — но не и готов инструмент за оценяване на съдържание, създадено с генеративни инструменти. | E47: Рамка на изложението — не изисква източник | H47: Изречението описва какво прави самата глава или обобщава вече изложеното. Това е организация на текста, а не твърдение за света. Оставя се както е. | I47: Claude (авт.) | J47: 29.08.2026
A48: 47 | B48: Изводи | C48: 113 | D48: В тази дефиниционна рамка съдържанието, създадено с генеративни инструменти, не представлява нов вид — то възпроизвежда познатите видове електронни ресурси, но с принципно различен процес на създаване и с различен профил на рисковете за качеството. | E48: Рамка на изложението — не изисква източник | H48: Изречението описва какво прави самата глава или обобщава вече изложеното. Това е организация на текста, а не твърдение за света. Оставя се както е. | I48: Claude (авт.) | J48: 29.08.2026
A49: 48 | B49: Изводи | C49: 114 | D49: Второ, педагогическите изисквания към електронното учебно съдържание — съответствие с учебните цели, издържана структура, достъпност, педагогически смислена интерактивност и пригодност за самостоятелно обучение — са формулирани независимо от начина на създаване и затова важат в пълна степен и за генерираното съдържание. | E49: Рамка на изложението — не изисква източник | H49: Изречението описва какво прави самата глава или обобщава вече изложеното. Това е организация на текста, а не твърдение за света. Оставя се както е. | I49: Claude (авт.) | J49: 29.08.2026
A50: 49 | B50: Изводи | C50: 118 | D50: Шесто, прегледът на съществуващите подходи показва и какво следва да бъде запазено от тях. | E50: Рамка на изложението — не изисква източник | H50: Изречението описва какво прави самата глава или обобщава вече изложеното. Това е организация на текста, а не твърдение за света. Оставя се както е. | I50: Claude (авт.) | J50: 29.08.2026
A51: 50 | B51: Изводи | C51: 118 | D51: Критериалната форма — йерархия от области, критерии и проверими показатели — е доказала приложимостта си в утвърдени инструменти за оценяване на онлайн курсове; педагогическата съдържателна основа е налична в доказателствено обоснованите принципи на мултимедийното учене и в първите принципи на обучението; а институционалната рамка осигурява средата, в която оценяването може да бъде въведено като задължителна практика. | E51: Покрито от цитата в същия абзац | F51: [32], [33], [29] | H51: И трите части на изречението вече имат източници другаде в главата: критериалната форма — [32], принципите на мултимедийното учене — [33], първите принципи — [29]. Повтори скобите в изводите. | I51: Claude (авт.) | J51: 29.08.2026
A52: 51 | B52: 1.2 | C52: 53 | D52: Петте области изисквания не се прилагат с еднаква тежест към всеки вид съдържание… Затова оценяването трябва да предвижда изрична стойност „неприложимо“… | E52: Пренаписан и изрично обозначен като решение на разработката | F52: — (не се твърди факт за света) | G52: — | H52: Предишната редакция твърдеше кои изисквания са „водещи“ при електронен урок, при тестови въпроси и при указания за самоподготовка — три емпирични твърдения без нито един източник. Пренаписан на 31.08.2026: остава само аналитичното наблюдение, че част от изискванията нямат предмет при даден вид материал, и изричното обозначение, че разпределението е решение на настоящата работа, операционализирано чрез стойността „неприложимо“ в модела от трета глава. | I52: Claude (авт.) | J52: 31.08.2026
A53: 52 | B53: 1.2 | C53: 54 (МТ) / 33 (НИП) | D53: Обемът на материала спрямо отделеното за него учебно време; материал, замислен за едно занятие, но написан с обем за три, е неизползваем в предвидената форма. | E53: Абзацът е премахнат | F53: — (не се твърди факт за света) | G53: — | H53: Няма източник за несъразмерността обем/учебно време, а показателят противоречи на т. 3.3 (П14 мери обема спрямо ЗАЯВЕНИЯ обем, а преобразуването в учебно време изрично не влиза в модела). Абзацът е премахнат, вместо да се пренаписва. | I53: Claude (авт.) | J53: 31.08.2026

Sheet Обобщение
B2: Ход на проверката
B4: Ниво 1 — библиографски записи
B5: Непроверено | C5: =COUNTIF('Ниво 1 Източници'!$K$2:$K$37,B5)
B6: Потвърдено | C6: =COUNTIF('Ниво 1 Източници'!$K$2:$K$37,B6)
B7: Частично потвърдено | C7: =COUNTIF('Ниво 1 Източници'!$K$2:$K$37,B7)
B8: Не се потвърждава | C8: =COUNTIF('Ниво 1 Източници'!$K$2:$K$37,B8)
B9: Източникът не е намерен | C9: =COUNTIF('Ниво 1 Източници'!$K$2:$K$37,B9)
B10: Няма достъп — за ръчна проверка | C10: =COUNTIF('Ниво 1 Източници'!$K$2:$K$37,B10)
B11: Готовност | C11: =(C6+C7)/36
B12: Ниво 2 — твърдения
B13: Непроверено | C13: =COUNTIF('Ниво 2 Твърдения'!$I$2:$I$65,B13)
B14: Потвърдено | C14: =COUNTIF('Ниво 2 Твърдения'!$I$2:$I$65,B14)
B15: Частично потвърдено | C15: =COUNTIF('Ниво 2 Твърдения'!$I$2:$I$65,B15)
B16: Не се потвърждава | C16: =COUNTIF('Ниво 2 Твърдения'!$I$2:$I$65,B16)
B17: Източникът не е намерен | C17: =COUNTIF('Ниво 2 Твърдения'!$I$2:$I$65,B17)
B18: Няма достъп — за ръчна проверка | C18: =COUNTIF('Ниво 2 Твърдения'!$I$2:$I$65,B18)
B19: Готовност | C19: =(C14+C15)/64
B21: Ниво 2 по приоритет (остават непроверени) | D21: от общо
B22: Критичен | C22: =COUNTIFS('Ниво 2 Твърдения'!$H$2:$H$65,B22,'Ниво 2 Твърдения'!$I$2:$I$65,"Непроверено") | D22: =COUNTIF('Ниво 2 Твърдения'!$H$2:$H$65,B22)
B23: Висок | C23: =COUNTIFS('Ниво 2 Твърдения'!$H$2:$H$65,B23,'Ниво 2 Твърдения'!$I$2:$I$65,"Непроверено") | D23: =COUNTIF('Ниво 2 Твърдения'!$H$2:$H$65,B23)
B24: Среден | C24: =COUNTIFS('Ниво 2 Твърдения'!$H$2:$H$65,B24,'Ниво 2 Твърдения'!$I$2:$I$65,"Непроверено") | D24: =COUNTIF('Ниво 2 Твърдения'!$H$2:$H$65,B24)
B25: Нисък | C25: =COUNTIFS('Ниво 2 Твърдения'!$H$2:$H$65,B25,'Ниво 2 Твърдения'!$I$2:$I$65,"Непроверено") | D25: =COUNTIF('Ниво 2 Твърдения'!$H$2:$H$65,B25)
B26: Ниво 3 — нецитирани твърдения
B27: Рамка — не изисква източник | C27: 14
B28: Покрито от съседен цитат | C28: 17
B29: ИЗИСКВА РЕШЕНИЕ | C29: 15
B30: Източник вече намерен | C30: 4

Sheet Гл.2–3 Ниво 1
A1: № | B1: Библиографски запис | C1: Тип | D1: Как се проверява | E1: Риск | F1: Брой твърдения | G1: Статус | H1: Линк | I1: Извадка | J1: Бележка | K1: Проверил | L1: Дата
A2: 13 | B2: Angular Team, "Angular versioning and releases," Angular Documentation, 2026. [Online]. Available: https://angular.dev/reference/releases | C2: Вендорска документация | D2: angular.dev — отваряне на раздела | E2: Критичен | F2: 2 | G2: Потвърдено | H2: https://angular.dev/reference/releases | I2: „Until Angular v22, Angular had a 6-month major release cycle, with 1-3 minor releases for each major release“; „A major release every 12 months“ с „4-6 minor releases“; поддръжка 24 месеца (12 активна + 12 LTS); „Deprecated API remain available through their deprecated phase, which lasts a minimum one major version (approximately one year).“ | J2: Тук употребата е коректна: твърдението е ЗА Angular, а не обобщение за софтуерните рамки изобщо. Вендорската документация е първоизточник за собствената си политика. ЕДНА КОРЕКЦИЯ: текстът казва „четири до шест междинни“ за новия цикъл — вярно; но за стария казва шестмесечен цикъл, а източникът уточнява „with 1-3 minor releases“ за него. | K2: Claude (авт.) | L2: 29.08.2026
A3: 15 | B3: CAST, Universal Design for Learning Guidelines, version 3.0. Lynnfield, MA, USA: CAST, 2024. [Online]. Available: https://udlguidelines.cast.org | C3: Рамка/насоки | D3: cast.org — UDL Guidelines 3.0 | E3: Нисък | F3: 1 | G3: Потвърдено | H3: https://udlguidelines.cast.org/ | I3: Трите принципа на UDL 3.0: „Design Multiple Means of Engagement“, „Design Multiple Means of Representation“, „Design Multiple Means of Action & Expression“. Издание 3.0 на CAST, 30 юли 2024 г. | J3: Потвърдено точно, включително годината и издателя. | K3: Claude (авт.) | L3: 29.08.2026
A4: 22 | B4: G. Kurdi, J. Leo, B. Parsia, U. Sattler, and S. Al-Emari, "A systematic review of automatic question generation for educational purposes," International Journal of Artificial Intelligence in Education, vol. 30, no. 1, pp. 121–204, 2020, doi: 10.1007/s40593-019-00186-y. | C4: Систематичен преглед | D4: DOI / издател | E4: Среден | F4: 1 | G4: Потвърдено | H4: https://link.springer.com/article/10.1007/s40593-019-00186-y | I4: Kurdi, Leo, Parsia, Sattler и Al-E‘mari, International Journal of Artificial Intelligence in Education, т. 30, кн. 1, с. 121–204, 2019. Прегледът обхваща 93 научни труда, публикувани между 2015 и началото на 2019 г. | J4: Числото 93 се потвърждава. ЗАБЕЛЕЖКА: записът в списъка трябва да се допълни с том, книжка и страници. | K4: Claude (авт.) | L4: 29.08.2026
A5: 23 | B5: G. W. Choi and J. Y. Seo, "Accessibility, usability, and universal design for learning: Discussion of three key LX/UX elements for inclusive learning design," TechTrends, vol. 68, no. 5, pp. 936–945, 2024, doi: 10.1007/s11528-024-00987-6. | C5: Статия | D5: DOI / издател | E5: Среден | F5: 1 | G5: Потвърдено | H5: https://link.springer.com/article/10.1007/s11528-024-00987-6 | I5: TechTrends, т. 68, кн. 5, с. 936–945, 2024. „a truly inclusive learning (i.e. UDL) comes from the interplay between them“ — достъпност, използваемост и UDL се допълват, а не се изключват. | J5: Записът е верен и твърдението се потвърждава. | K5: Claude (авт.) | L5: 29.08.2026
A6: 34 | B6: M. Hadra, K. Cambridge, and M. Mesbah, "Evaluating the accuracy and reliability of AI content detectors in academic contexts," International Journal for Educational Integrity, vol. 22, Art. no. 4, 2026, doi: 10.1007/s40979-026-00213-1. | C6: Статия | D6: DOI / издател | E6: Висок | F6: 1 | G6: Потвърдено | H6: https://link.springer.com/article/10.1007/s40979-026-00213-1 | I6: „Turnitin demonstrated strong performance in identifying Human-generated texts… but its specificity for this class was comparatively low, indicating frequent misclassification“; „its sensitivity was substantially lower, suggesting that many AI texts were not correctly identified“; „paraphrasing severely degrades detector reliability“; риск от „misclassifying legitimate EFL student work“. Точност: Originality 0,69 срещу Turnitin 0,61. | J6: Потвърдено изцяло. ЗАБЕЛЕЖКА: записът дава „Art. no. 4“, а OpenAlex отчита кн. 1 — да се сверя по самата статия. | K6: Claude (авт.) | L6: 29.08.2026
A7: 35 | B7: M. Perkins, "Academic integrity considerations of AI large language models in the post-pandemic era: ChatGPT and beyond," Journal of University Teaching & Learning Practice, vol. 20, no. 2, Art. no. 7, 2023, doi: 10.53761/1.20.02.07. | C7: Статия | D7: DOI / издател | E7: Среден | F7: 1 | G7: Потвърдено | H7: https://openjournals.libs.uga.edu/jutlp/article/view/3212 | I7: Journal of University Teaching and Learning Practice, т. 20, кн. 2, чл. 07, 2023. Изводът е, че институциите трябва да актуализират политиките си за академична почтеност и че критично е не самото използване на инструменти, а начинът на приложението им. | J7: Записът е верен. Твърдението за изместване към регулирана и декларирана употреба се потвърждава по същество. | K7: Claude (авт.) | L7: 29.08.2026
A8: 38 | B8: P. Denny, H. Khosravi, A. Hellas, J. Leinonen, and S. Sarsa, "Can we trust AI-generated educational content? Comparative analysis of human and AI-generated learning resources," 2023, arXiv:2306.10509. | C8: Статия | D8: DOI / издател | E8: Висок | F8: 2 | G8: Частично потвърдено | H8: https://arxiv.org/abs/2306.10509 | I8: „the quality of AI-generated resources, as perceived by students, is equivalent to the quality of resources generated by their peers“. Абстрактът не дава числа. | J8: ВАЖНО РАЗЛИЧИЕ: източникът твърди РАВНОСТОЙНО ВЪЗПРИЕМАНО КАЧЕСТВО, а не „неразличимост по повърхностни белези“. Второто е по-силно и не се подкрепя. Виж редове 6 и 25 на Ниво 2. | K8: Claude (авт.) | L8: 29.08.2026
A9: 39 | B9: Plain Language — Part 1: Governing Principles and Guidelines, ISO 24495-1:2023, International Organization for Standardization, Geneva, Switzerland, 2023. | C9: Стандарт | D9: ISO 24495-1:2023 — платен достъп | E9: Висок | F9: 1 | G9: Потвърдено | H9: https://webstore.ansi.org/preview-pages/ISO/preview_ISO+24495-1-2023.pdf | I9: Четирите принципа: 1) Relevant — „Readers get what they need“; 2) Findable — „Readers can easily find what they need“; 3) Understandable — „Readers can easily understand what they find“; 4) Usable — „Readers can easily use the information“. | J9: Потвърдено чрез свободната предварителна страница на стандарта. Четирите принципа съвпадат точно с формулировката в текста. | K9: Claude (авт.) | L9: 29.08.2026
A10: 40 | B10: Q. Huang, C. Lv, L. Lu, and S. Tu, "Evaluating the quality of AI-generated digital educational resources for university teaching and learning," Systems, vol. 13, no. 3, Art. no. 174, 2025, doi: 10.3390/systems13030174. | C10: Статия | D10: DOI / издател | E10: Висок | F10: 1 | G10: Частично потвърдено | H10: https://www.mdpi.com/2079-8954/13/3/174 | I10: „this paper presents an evaluation index system for AI-generated digital educational resources by combining the Delphi method and the Analytic Hierarchy Process“. Системата има ЧЕТИРИ измерения и двадесет показателя: съдържателни (тегло 0,503), на изразяването (0,257), потребителски (0,137) и технически (0,109). | J10: РАЗЛИЧИЕ: текстът говори за „съдържателни, педагогически и технологични“ измерения. Източникът има четири измерения и сред тях НЯМА педагогическо — има „изразяване“ и „потребителски“. Освен това методът е Delphi плюс AHP, което заслужава да се назове. | K10: Claude (авт.) | L10: 29.08.2026
A11: 47 | B11: W. H. Walters and E. I. Wilder, "Fabrication and errors in the bibliographic citations generated by ChatGPT," Scientific Reports, vol. 13, 2023, doi: 10.1038/s41598-023-41032-5. | C11: Статия | D11: DOI / издател | E11: Критичен | F11: 1 | G11: Потвърдено | H11: https://www.nature.com/articles/s41598-023-41032-5 | I11: „55% of the GPT-3.5 citations but just 18% of the GPT-4 citations are fabricated“; „43% of the real (non-fabricated) GPT-3.5 citations but just 24% of the real GPT-4 citations include substantive citation errors“. Scientific Reports, т. 13, чл. 14045, 2023. | J11: И трите числа в текста се потвърждават дословно. ПРЕПОРЪКА: „съществена част съдържа значими грешки“ да се замени с конкретните 43 и 24 на сто — числата са налични и са по-силни от общата формулировка. | K11: Claude (авт.) | L11: 29.08.2026

Sheet Гл.2–3 Ниво 2
A1: № | B1: Раздел | C1: Абзац | D1: Източник(ци) | E1: Локатор | F1: Твърдение (както е в документа) | G1: Статус | H1: Намерено на | I1: Линк | J1: Извадка от източника (дословно) | K1: Бележка / действие | L1: Проверил | M1: Дата
A2: 1 | B2: 2.1 | C2: 147 | D2: [7] | F2: Към това семейство принадлежи и българският принос по темата: цитираното изследване на проблемите и решенията при генеративния изкуствен интелект в образованието очертава контурите на интегрирана система за оценяване на качеството на генерирани материали, съчетаваща метрики за кохезия, кохерентност, четивност и оригиналност с експертен преглед [7]. | G2: Потвърдено | H2: — | I2: https://journals.azbuki.bg/pedagogy/generativen-izkustven-intelekt-v-obrazovanieto-problemi-i-reseniya/view | J2: Източникът изброява „кохезия и кохерентност, четливост и сходство“, като разгръща семантичното сходство като отделна метрика. „Оригиналност“ не се среща. | K2: ПОПРАВЕНО В ТЕКСТА: „оригиналност“ стана „семантично сходство“. Първа глава го цитираше правилно — глава 2 не. | L2: Claude (авт.) | M2: 29.08.2026
A3: 2 | B3: 2.1 | C3: 148 | D3: [40] | F3: Показателен пример е изследването на Huang и колектив, което конструира и апробира подход за оценяване на качеството на AI-генерирани дигитални образователни ресурси във висшето образование, съчетаващ множество измерения на качеството — съдържателни, педагогически и технологични — в единна оценъчна процедура [40]. | G3: Потвърдено | H3: — | I3: https://www.mdpi.com/2079-8954/13/3/174 | J3: „an evaluation index system … combining the Delphi method and the Analytic Hierarchy Process“; четири измерения и двадесет показателя, с тегла 0,503 / 0,257 / 0,137 / 0,109. | K3: ПОПРАВЕНО: „съдържателни, педагогически и технологични“ стана четирите действителни измерения, добавен е и методът. | L3: Claude (авт.) | M3: 29.08.2026
A4: 3 | B4: 2.1 | C4: 149 | D4: [26]; [51] | F4: Системите от типа на COGENT налагат педагогически ограничения още при създаването на съдържанието [51], а мулти-агентните архитектури като Instructional Agents включват вътрешни роли за преглед и проверка на произведените материали [26]. | G4: Потвърдено | H4: — | I4: https://arxiv.org/abs/2508.19611 | J4: „Instructional Agents simulates role-based collaboration to ensure pedagogical coherence“; материалите „are reviewed and refined by teaching faculty prior to use“. COGENT: „we incorporate structured curriculum information … ensuring pedagogical alignment“. | K4: ПОПРАВЕНО: „вътрешни роли за преглед и проверка“ не се потвърждава — прегледът в източника е ЧОВЕШКИ, от преподавател преди употреба. Текстът вече казва това. | L4: Claude (авт.) | M4: 29.08.2026
A5: 4 | B5: 2.1 | C5: 149 | D5: [45] | F5: На институционално равнище същата логика се проявява в рамки, които интегрират изкуствения интелект в системите за осигуряване на качеството на висшето образование [45]. | G5: Частично потвърдено | H5: — | I5: https://www.emerald.com/qae/article/34/2/205/1302250/Enhancing-quality-assurance-through-strategic | J5: Петстъпков модел за внедряване на ИИ в институционалната рамка за качество. | K5: Потвърдено — същият източник и същото твърдение като в първа глава. || ОТКРИТ ПРОБЛЕМ 31.08.2026: няма дословна извадка — статията в Emerald е зад платен достъп и не може да бъде прочетена автоматично. Твърдението остава подкрепено само от резюмето. Нужен е достъп през университета или замяна на източника. | L5: Claude (авт.) | M5: 29.08.2026
A6: 5 | B6: 2.2 | C6: 154 | D6: [19] | F6: От една страна, халюцинациите правят възможни грешки от вид, който при добросъвестен човешки автор практически не се среща — уверено формулирани, но изцяло измислени факти, данни и източници [19]. | G6: Потвърдено | H6: — | I6: https://arxiv.org/html/2311.05232v3 | J6: Систематизацията на халюцинациите определя фактологичните халюцинации като изход, съдържащ факти, несъвместими с действителността или непроверими. | K6: ПОПРАВЕН ИЗТОЧНИК: беше [19] Kasneci, който НЕ обсъжда халюцинации и измислени източници. Пренасочено към [31] — систематизацията на халюцинациите. | L6: Claude (авт.) | M6: 29.08.2026
A7: 6 | B7: 2.2 | C7: 154 | D7: [38] | F7: От друга страна, тези грешки не са маркирани стилистично: сравнителните изследвания показват, че генерираните учебни ресурси са трудно различими от човешките по възприемано качество и повърхностни белези [38]. | G7: Потвърдено | H7: — | I7: https://arxiv.org/abs/2306.10509 | J7: „the quality of AI-generated resources, as perceived by students, is equivalent to the quality of resources generated by their peers“. | K7: ПОПРАВЕНО: „трудно различими по възприемано качество и повърхностни белези“ стана „възприеманото от студентите качество е равностойно“. Неразличимостта не се твърди от източника. | L7: Claude (авт.) | M7: 29.08.2026
A8: 7 | B8: 2.2 | C8: 156 | D8: [13] | F8: Рамката Angular е показателен пример: до версия 22 тя следва шестмесечен цикъл на основните издания, като от версия 22 преминава към едно основно издание годишно с четири до шест междинни; всяко основно издание се поддържа двадесет и четири месеца, а отпадащите програмни интерфейси преминават през период на отпадане с продължителност поне едно основно издание [13]. | G8: Частично потвърдено | H8: — | I8: https://angular.dev/reference/releases | J8: „Until Angular v22, Angular had a 6-month major release cycle, with 1-3 minor releases for each major release“; „A major release every 12 months“ с „4-6 minor releases“; 24 месеца поддръжка; отпадане „a minimum one major version (approximately one year)“. | K8: Всички елементи се потвърждават. Липсва само уточнението, че при стария шестмесечен цикъл междинните издания са били едно до три. Може да се добави или да се пропусне без загуба. | L8: Claude (авт.) | M8: 29.08.2026
A9: 8 | B9: 2.2 | C9: 158 | D9: [19] | F9: Генерираният текст може да се позовава на несъществуващи публикации или да приписва на реални източници твърдения, които те не съдържат — дефект, познат и документиран в литературата за халюцинациите [19]. | G9: Потвърдено | H9: — | I9: https://www.nature.com/articles/s41598-023-41032-5 | J9: „55% of the GPT-3.5 citations but just 18% of the GPT-4 citations are fabricated“. | K9: ПОПРАВЕН ИЗТОЧНИК И УСИЛЕНО ТВЪРДЕНИЕ: беше обща препратка към [19], който не съдържа това. Сега стъпва на [47] с конкретните числа. | L9: Claude (авт.) | M9: 29.08.2026
A10: 9 | B10: 2.2 | C10: 159 | D10: [47] | F10: Изследване върху 636 библиографски позовавания, генерирани от два широко използвани диалогови модела, установява, че при по-стария модел 55% от цитатите са изцяло измислени, а при по-новия — 18%, като и сред реално съществуващите цитати съществена част съдържа значими грешки [47]. | G10: Потвърдено | H10: — | I10: https://www.nature.com/articles/s41598-023-41032-5 | J10: „43% of the real (non-fabricated) GPT-3.5 citations but just 24% of the real GPT-4 citations include substantive citation errors“. | K10: ДОПЪЛНЕНО: общата формулировка е заменена с конкретните 43 и 24 на сто. | L10: Claude (авт.) | M10: 29.08.2026
A11: 10 | B11: 2.3 | C11: 163 | D11: [44] | F11: Вторият е педагогическата логика на изложението — последователност, съответстваща на учебната логика на дисциплината, сегментиране на смислови единици и въвеждане на понятията преди употребата им [44]; проверимият показател е дали обучаем с декларираните предварителни знания може да следва изложението, без да се натъква на неизведени понятия. | G11: Потвърдено | H11: — | I11: https://www.sciencedirect.com/science/article/pii/S2211368121000231 | J11: „when a complex slide is broken down into a progression of added parts (i.e., segmenting principle)“; „pre-training (provide pre-training in the names and characteristics of key concepts)“. | K11: ПОПРАВЕН НОМЕР: цитатът сочеше [44] Ramezani вместо [42] Mayer — грешка от преномерирането при сливането. Съдържанието се потвърждава. | L11: Claude (авт.) | M11: 29.08.2026
A12: 11 | B12: 2.3 | C12: 163 | D12: [33] | E12: с. 44–45 | F12: Третият критерий е активното учене: наличие на примери, задачи за прилагане и съдържателна обратна връзка — операционализация на принципите за демонстрация и прилагане [33, с. 44–45]. | G12: Потвърдено (ниво на статия) | H12: Springer / OpenAlex — резюме на статията | I12: https://link.springer.com/article/10.1007/BF02505024 | J12: Резюмето изброява петте принципа дословно: „Learning is promoted when learners are engaged in solving real-world problems… when existing knowledge is activated as a foundation for new knowledge… when new knowledge is demonstrated to the learner… when new knowledge is applied by the learner… when new knowledge is integrated into the learner’s world.“ | K12: Принципите за демонстрация и прилагане се потвърждават. Локаторът „с. 44–45“ да се сверя по PDF пагинацията. || 31.08.2026: източникът вече е [29] по текущата номерация (тук е записан по стара като [33]). Локаторът „с. 44–45“ е ПРЕМАХНАТ от текста — пълният текст на статията е недостъпен и пагинацията не може да се провери; цитира се цялата статия. | L12: Claude (авт.) | M12: 29.08.2026
A13: 12 | B13: 2.3 | C13: 164 | D13: [51] | F13: Опитът на системите за контролирано генериране потвърждава това от обратната страна: за да бъде генерираното съдържание съобразено с учебната програма и с равнището на обучаемите, тези ограничения трябва да бъдат вградени изрично в процеса на генериране [51] — а при масовата практика на диалогово създаване такова вграждане липсва, освен ако преподавателят не го е внесъл сам чрез заявката. | G13: Потвърдено | H13: — | I13: https://aclanthology.org/2025.bea-1.10.pdf | J13: „we implement constraints on word number, vocabulary, and sentence complexity based on grade-level reading proficiency“. | K13: Потвърдено: ограниченията са вградени изрично в процеса на генериране. | L13: Claude (авт.) | M13: 29.08.2026
A14: 13 | B14: 2.3 | C14: 165 | D14: [22] | F14: Систематичният преглед на 93 изследвания в тази област показва, че още преди големите езикови модели полето е разработило подробни изисквания към качеството на генерираните въпроси — свързаност с учебното съдържание, еднозначност на верния отговор, правдоподобност на грешните алтернативи — и че оценяването им системно изисква човешка експертна проверка [22]. | G14: Частично потвърдено | H14: IJAIED 30(1) — резюме и раздел за оценяване | I14: https://link.springer.com/article/10.1007/s40593-019-00186-y | J14: „This review extends a previous review on AQG literature that has been published up to late 2014. It includes 93 papers that were between 2015 and early 2019 and tackle the automatic generation of questions for educational purposes.“ | Оценявани свойства на въпросите: граматическа правилност („36.7% and 39.5% of questions generated… were rated by reviewers as ungrammatical and nonsensical“), трудност („there is little focus in the current literature on generating questions of controlled difficulty“), отговоримост, естественост на формулировката („enhancing the naturalness of questions (i.e. verbalisation)“) и качество на дистракторите („Distractor generation is a very important task in MCQ generation since distractors influence question quality“). | Човешка оценка: критерий за качество Q9 — „whether questions were evaluated by multiple reviewers and whether measures of the agreement… were reported“. | K14: Числото 93 се потвърждава. || ВНИМАНИЕ — НЕСЪОТВЕТСТВИЕ С ТЕКСТА. Абз. 164 приписва на прегледа триадата „свързаност с учебното съдържание, еднозначност на верния отговор, правдоподобност на грешните алтернативи“. Дословно потвърдени са само качеството на дистракторите и (косвено) отговоримостта; „свързаност с учебното съдържание“ не се среща като изведен критерий. Изречението подлежи на пренаписване по действително изброените свойства. 31.08.2026. | L14: Claude (авт.) | M14: 29.08.2026
A15: 14 | B15: 2.3 | C15: 166 | D15: [2] | F15: Документираният опит с автоматизирано генериране на тестови въпроси показва системна склонност на моделите да формулират задачи по отделен детайл от подадения текст, вместо по водещото понятие, което той изгражда — дефект, който наложил въвеждането на изрична настройка за концептуална дълбочина в работния процес [2]. | G15: Потвърдено | H15: — | I15: https://www.conf-dte.bg/docs/2026/p-100.pdf | J15: „без явно зададена дълбочина AI моделите създават тясно-…“; „Именно тази наблюдавана слабост е обусловила въвеждането на Стъпка 2 от работния процес — конфигурирането на концептуалната дълбочина на въпроса.“ | K15: Потвърдено дословно, включително причинната връзка. | L15: Claude (авт.) | M15: 29.08.2026
A16: 15 | B16: 2.4 | C16: 171 | D16: [19] | F16: Спецификата на генерираното съдържание тук е парадоксална: езикът му е плавен по подразбиране, затова рискът не е в очевидната неграмотност, а в по-фини дефекти — терминологична непоследователност между отделни части на материала, произведени с различни заявки; стилова монотонност, която уморява при по-дълго изложение; а при езици с по-слабо покритие в обучителните данни, каквито са и по-малките европейски езици, — неестествени конструкции и буквално пренесени чуждоезични обрати [19]. | G16: Потвърдено | H16: — | I16: https://opus.bibliothek.uni-augsburg.de/opus4/files/109030/109030.pdf | J16: „While the majority of the research in large language models is done for the English language, there is still a gap of research in this field for other languages.“ Плюс таблицата на [2]: ~4–5 % срещу ~1–2 % редакция. | K16: ПРЕНАПИСАНО: „терминологична непоследователност между заявки“ и „стилова монотонност“ не се твърдят от [19] и отпаднаха. Езиковият дефицит остана и получи втора опора — документираните български данни от [2]. | L16: Claude (авт.) | M16: 29.08.2026
A17: 16 | B17: 2.4 | C17: 172 | D17: [39] | F17: Критерият за разбираемост има и международно утвърдена операционализация: стандартът за ясен език ISO 24495-1 определя ясната комуникация чрез четири принципа, които поставят читателя в центъра — читателят да получава относимата за него информация, да може да я намери, да я разбере и да може да я използва [39]. | G17: Потвърдено | H17: — | I17: https://webstore.ansi.org/preview-pages/ISO/preview_ISO+24495-1-2023.pdf | J17: „Readers get what they need“; „Readers can easily find what they need“; „Readers can easily understand what they find“; „Readers can easily use the information“. | K17: Четирите принципа съвпадат дословно с формулировката в текста. | L17: Claude (авт.) | M17: 29.08.2026
A18: 17 | B18: 2.4 | C18: 173 | D18: [2] | F18: При съпоставимо по обем генериране на тестови въпроси от учебен текст на два езика делът на въпросите, изискващи редакция, е около 4–5 на сто при българските срещу 1–2 на сто при английските, а преобладаващият тип нередност е именно неестествено или несвойствено формулиране на български [2]. | G18: Потвърдено | H18: — | I18: https://www.conf-dte.bg/docs/2026/p-100.pdf | J18: Таблица: български 324 920 знака → 267 въпроса → ~4–5 % редакция; английски 331 893 знака → 286 въпроса → ~1–2 %. „необходимите корекции са предимно от езиков и стилистичен, а не от фактически характер“. | K18: И трите елемента се потвърждават точно — двата дяла и преобладаващият тип нередност. | L18: Claude (авт.) | M18: 29.08.2026
A19: 18 | B19: 2.4 | C19: 174 | D19: [44] | F19: Текстовата и визуалната организация обхваща разчленяването на изложението — заглавия, които отразяват съдържанието, смислово обособени части, откроени определения и примери — и икономията на изразните средства: изследванията върху мултимедийното учене показват, че изключването на несъществения текст и на ненужния визуален материал подобрява ученето [44]. | G19: Потвърдено | H19: — | I19: https://www.sciencedirect.com/science/article/pii/S2211368121000231 | J19: „students learn better when extraneous comments and unneeded visual material are excluded (i.e., coherence principle)“. | K19: ПОПРАВЕН НОМЕР: същата грешка като ред 10 — сочеше [44] вместо [42]. | L19: Claude (авт.) | M19: 29.08.2026
A20: 19 | B20: 2.4 | C20: 175 | D20: [15] | F20: Рамката на универсалния дизайн за учене (UDL) изисква учебното съдържание да предоставя множество средства за представяне на информацията, за ангажиране на обучаемите и за изразяване на наученото, така че материалът да бъде използваем от обучаеми с различни възможности и предпочитания [15]. | G20: Потвърдено | H20: — | I20: https://udlguidelines.cast.org | J20: „Design Multiple Means of Engagement“, „Design Multiple Means of Representation“, „Design Multiple Means of Action & Expression“. | K20: Трите средства се потвърждават дословно. | L20: Claude (авт.) | M20: 29.08.2026
A21: 20 | B21: 2.4 | C21: 175 | D21: [23] | F21: В литературата за дизайна на учебния опит достъпността, използваемостта и универсалният дизайн се разглеждат като три допълващи се елемента на приобщаващия дизайн — свързани, но неподменяеми един с друг [23]. | G21: Потвърдено | H21: — | I21: https://link.springer.com/article/10.1007/s11528-024-00987-6 | J21: „a truly inclusive learning (i.e. UDL) comes from the interplay between them“. | K21: Потвърдено: трите елемента са допълващи се и неподменяеми. | L21: Claude (авт.) | M21: 29.08.2026
A22: 21 | B22: 2.5 | C22: 180 | D22: [34] | F22: Емпиричните оценки обаче показват, че точността и надеждността на такива детектори в академичен контекст са недостатъчни — те произвеждат както фалшиви обвинения срещу човешки текст, така и пропуски на действително генериран, а резултатите им се влияят от езика и от редакцията на текста [34]. | G22: Потвърдено | H22: — | I22: https://link.springer.com/article/10.1007/s40979-026-00213-1 | J22: Ниска специфичност при човешки текст, съществено по-ниска чувствителност при машинен, „paraphrasing severely degrades detector reliability“, риск при текст на неносители на езика. | K22: Потвърдено изцяло, включително влиянието на езика и на редакцията. Може да се добавят стойностите за точност — 0,69 и 0,61. | L22: Claude (авт.) | M22: 29.08.2026
A23: 22 | B23: 2.5 | C23: 181 | D23: [1] | F23: Анализът на приложимостта им в българска академична среда посочва два системни проблема: фалшивите положителни резултати са особено характерни за текстове с висока терминологична наситеност и формализиран стил — тоест точно за добре написаното научно и учебно изложение — а детекторите, обучени предимно върху текстове на английски език, губят точност при проверка на текстове на български [1]. | G23: Потвърдено | H23: — | I23: https://www.conf-dte.bg/docs/2026/p-2.pdf | J23: „Фалшивите положителни резултати са особено характерни за текстове с висока терминологична наситеност, академичен жаргон и формализиран стил“; „детекторите, обучени предимно върху текстове на английски език“. | K23: Потвърдено дословно, включително и двата системни проблема. | L23: Claude (авт.) | M23: 29.08.2026
A24: 23 | B24: 2.5 | C24: 182 | D24: [35] | F24: Анализите на академичната почтеност след масовото навлизане на диалоговите модели показват изместване от първоначалните забрани към регулирана и декларирана употреба: постижимата цел не е откриването на всяка генерирана дума, а ясни правила кога употребата е допустима, как се декларира и кой носи отговорност за крайния текст [35]. | G24: Потвърдено | H24: JUTLP 20(2), 2023 — резюме и заключение | I24: https://open-publishing.org/journals/index.php/jutlp/article/view/635 | J24: „…it is not the student use of any AI tools that defines whether plagiarism or a breach of academic integrity has occurred, but whether any use is made clear by the student.“ | „…academic integrity policies of any given HEI, which must be updated to consider how these tools will be used in future educational environments.“ | „…these tools have in creating original, coherent text that can avoid detection by existing technological methods of detection and trained academic staff alike.“ | K24: Потвърдено по същество. || 31.08.2026: предишната „извадка“ беше преразказ. Заменена с дословния текст. И трите елемента на твърдението — недостатъчност на откриването, актуализиране на политиките, декларирана употреба — се покриват. | L24: Claude (авт.) | M24: 29.08.2026
... A30: 29 | B30: 3.7 | C30: 254 | D30: [13] | F30: Обстоятелството е особено благоприятно за целите на апробирането: към момента на генериране на материалите основното издание Angular 22 е публикувано само няколко седмици по-рано [13], тоест почти сигурно е извън обучителните данни и на двата използвани инструмента. | G30: Потвърдено | H30: — | I30: https://angular.dev/reference/releases | J30: Angular v22 е издадена на 3 юни 2026 г. | K30: Твърдението за времевата близост се потвърждава от графика на изданията. При окончателната редакция сверете датата на генериране на материалите. | L30: Claude (авт.) | M30: 29.08.2026

Sheet Гл.2–3 Ниво 3
A1: № | B1: Раздел | C1: Абзац | D1: Изречение без цитат | E1: Решение | F1: Бележка | G1: Проверил | H1: Дата
A2: 1 | B2: 2.1 | C2: 146 | D2: Първото семейство адаптира наследената критериална традиция: съществуващите системи от критерии за качество на електронно съдържание — педагогически, езикови, визуални — се прилагат към генерираните материали без съществена промяна. | E2: Рамка на изложението — не изисква източник | F2: Описание на собствения модел, на процедурата или на организацията на изложението. В глави 2 и 3 това е самият резултат на работата, а не твърдение за света. Не изисква източник. | G2: Claude (авт.) | H2: 29.08.2026
A3: 2 | B3: 2.2 | C3: 153 | D3: Научната коректност е първата и базова област на качеството: учебен материал, който съобщава неверни факти, компрометира самата цел на обучението, независимо колко добре е структуриран и оформен. | E3: Покрито от цитата в същия абзац | F3: Изречението продължава или тълкува твърдение, цитирано в същия абзац. Повтори скобата, ако абзацът е дълъг. | G3: Claude (авт.) | H3: 29.08.2026
A4: 3 | B4: 2.2 | C4: 154 | D4: Следствието за критериите е принципно — проверката на точността не може да разчита на усета на четящия за „съмнителен текст", а трябва да се извършва твърдение по твърдение, срещу независими източници: учебна литература, официална документация, стандарти. | E4: Покрито от цитата в същия абзац | F4: Изречението продължава или тълкува твърдение, цитирано в същия абзац. Повтори скобата, ако абзацът е дълъг. | G4: Claude (авт.) | H4: 29.08.2026
A5: 4 | B5: 2.2 | C5: 155 | D5: Актуалността произтича от начина на обучение на езиковите модели: техните знания отразяват състоянието на обучителните данни към минал момент и не се обновяват сами. | E5: Нужен източник — намерен | F5: НАНЕСЕНО: остарялото знание вече стъпва на [49] — систематизацията на обогатеното с извличане генериране го посочва сред основните ограничения на моделите. | G5: Claude (авт.) | H5: 29.08.2026
A6: 5 | B6: 2.2 | C6: 155 | D6: Показателят, който критерият изисква, е съответствие на съдържанието с актуалното състояние на областта — актуална версия, действащ стандарт, съвременна терминология — проверено към момента на използване, а не към момента на генериране. | E6: Покрито от цитата в същия абзац | F6: Изречението продължава или тълкува твърдение, цитирано в същия абзац. Повтори скобата, ако абзацът е дълъг. | G6: Claude (авт.) | H6: 29.08.2026
A7: 6 | B7: 2.2 | C7: 156 | D7: Първото е количествено: за период от три години — типичното време между обучението на един езиков модел и използването на негов изход — предметната област е сменила няколко основни издания, а част от препоръчаните практики са отпаднали. | E7: Пренаписано | F7: НАНЕСЕНО: „за период от три години — типичното време между обучението на модел и използването на негов изход“ отпадна. Това число нямаше източник и се четеше като установен факт. Остана „дори за няколко години“. | G7: Claude (авт.) | H7: 29.08.2026
A8: 7 | B8: 2.2 | C8: 157 | D8: Оттук произтича и практическото изискване към показателя за актуалност: той не може да бъде прилаган абстрактно, а изисква изрично фиксирана отправна точка — коя версия на технологията, кое издание на стандарта или коя редакция на нормативния документ се приема за актуални към момента на оценяването. | E8: Покрито от цитата в същия абзац | F8: Изречението продължава или тълкува твърдение, цитирано в същия абзац. Повтори скобата, ако абзацът е дълъг. | G8: Claude (авт.) | H8: 29.08.2026
A9: 8 | B9: 2.2 | C9: 159 | D9: Данните показват две неща едновременно: че новите поколения модели намаляват честотата на измислените източници и че дори при най-добрите тя остава далеч от пренебрежима. | E9: Покрито от цитата в същия абзац | F9: Изречението продължава или тълкува твърдение, цитирано в същия абзац. Повтори скобата, ако абзацът е дълъг. | G9: Claude (авт.) | H9: 29.08.2026
A10: 9 | B10: 2.2 | C10: 160 | D10: Обобщено, критериите за научна коректност на генерираното учебно съдържание не се различават по форма от класическите — точност, актуалност, надеждност, съответствие с източниците — но операционализацията им се обръща: от презумпция за коректност, оборвана по изключение, към проверка на всяко съществено твърдение, при която коректността се установява, а не се предполага. | E10: Рамка на изложението — не изисква източник | F10: Описание на собствения модел, на процедурата или на организацията на изложението. В глави 2 и 3 това е самият резултат на работата, а не твърдение за света. Не изисква източник. | G10: Claude (авт.) | H10: 29.08.2026
A11: 10 | B11: 2.3 | C11: 162 | D11: Дидактическата пригодност е втората област на качеството и е логически независима от първата: материал с безупречна фактология може да бъде негоден за обучение — зле подреден, несъобразен с аудиторията, лишен от упражнения и обратна връзка. | E11: Рамка на изложението — не изисква източник | F11: Описание на собствения модел, на процедурата или на организацията на изложението. В глави 2 и 3 това е самият резултат на работата, а не твърдение за света. Не изисква източник. | G11: Claude (авт.) | H11: 29.08.2026
A12: 11 | B12: 2.3 | C12: 167 | D12: Проверката трябва да установи дали материалът е използваем такъв, какъвто е, в конкретните условия — вписва ли се в отделеното учебно време, съответства ли на формата на обучението, стъпва ли на действително изучаваното преди него и подготвя ли следващото. | E12: Покрито от цитата в същия абзац | F12: Изречението продължава или тълкува твърдение, цитирано в същия абзац. Повтори скобата, ако абзацът е дълъг. | G12: Claude (авт.) | H12: 29.08.2026
A13: 12 | B13: 2.4 | C13: 172 | D13: При генериран текст стандартът е полезен именно защото разграничава плавността от яснотата — текст, който се чете гладко, може да не отговаря на нито един от четирите принципа. | E13: Покрито от цитата в същия абзац | F13: Изречението продължава или тълкува твърдение, цитирано в същия абзац. Повтори скобата, ако абзацът е дълъг. | G13: Claude (авт.) | H13: 29.08.2026
... A60: 59 | B60: 3.7 | C60: 257 | D60: Трето, опит в обучението и наставничеството на по-млади специалисти, който осигурява необходимия за дидактическите показатели поглед върху типичните затруднения на начинаещите в тази предметна област. | E60: Рамка на изложението — не изисква източник | F60: Описание на собствения модел, на процедурата или на организацията на изложението. В глави 2 и 3 това е самият резултат на работата, а не твърдение за света. Не изисква източник. | G60: Claude (авт.) | H60: 29.08.2026

Sheet Корекции 31.08
A1: № | B1: Файл | C1: Раздел / абзац | D1: Какво беше | E1: Какво стана | F1: Основание | G1: Източник | H1: Извадка от източника (дословно) | I1: Линк | J1: Дата
A2: 1 | B2: МТ + НИП | C2: 1.1, абз. 46 (МТ) / 25 (НИП) | D2: Тялото на Таблица 1 „Класификационни оси“ стоеше в края на първа глава, далеч от надписа си (следствие от сливането: скриптът обхождаше само абзаци, не и таблици). | E2: XML възелът на таблицата е преместен непосредствено след надписа. Проверено и за останалите таблици — Таблица 2 беше със същия дефект и също е преместена. | F2: Технически дефект от сливането, не съдържателен. | G2: — | H2: — | I2: — | J2: 31.08.2026
A3: 2 | B3: МТ + НИП | C3: 1.1, абз. 44 (МТ) / 23 (НИП) | D3: „Институционално създаваното съдържание — учебници, официални курсове — по правило преминава редакционен и рецензионен процес; съдържанието, създавано от отделния преподавател… ; съдържанието, създавано от самите обучаеми… Генеративно създаденото съдържание е единственият масов вид, който по подразбиране не преминава през никакъв утвърден контролен механизъм.“ — нито едно от четирите твърдения не беше покрито от източник. | E3: Абзацът е пренаписан изцяло около това, което ръководството на 1EdTech действително постановява: изискването за човешка валидация и най-високото равнище от скалата, при което съдържанието се публикува без надзор. Несравненията по произход отпадат. | F3: Правило: всяко твърдение, което не е собствен извод, се подкрепя с източник. | G3: [49] в МТ / [12] в НИП — AI-Generated Content Best Practices v1.0, 1EdTech, 2025 | H3: „AI-generated content requires human validation to ensure accuracy, rigor, and alignment with standards.“ | „AI-generated content cannot be used ‘as is’ for high-stakes or learning-critical contexts without subject matter expert validation.“ | „An organization’s staff, educators, or SMEs should fact-check content for accuracy, evaluate for potential bias, and review for accessibility compliance.“ | Равнище 5 — Fully AI-Generated: „GenAI autonomously generates and publishes content with minimal or no human oversight.“ | I3: https://www.imsglobal.org/resource/AI-Generated_Content_Best_Practices/v1p0 | J3: 31.08.2026
A4: 3 | B4: МТ + НИП | C4: 1.1, абз. 45 (МТ) / 24 (НИП) | D4: „…ще се съсредоточи върху два-три вида електронно учебно съдържание…“ | E4: „…върху три вида…“ — изречението веднага изброява точно три и продължава с „трите основни функции“. | F4: Вътрешно несъответствие в изречението. | G4: — | H4: — | I4: — | J4: 31.08.2026
A5: 4 | B5: МТ + НИП | C5: 1.2, абз. 49 (МТ) / 28 (НИП) | D5: „…включването на съдържание, което не обслужва нито една цел, е дефект, а не богатство.“ | E5: „…съдържание, което не обслужва нито една формулирана цел, няма учебно основание да присъства.“ | F5: Противопоставянето „богатство“ не е нито твърдение на източник, нито теза, която някой поддържа — реторична фигура без адресат. | G5: — | H5: — | I5: — | J5: 31.08.2026
A6: 5 | B6: МТ + НИП | C6: 1.2, абз. 49 и 163 (МТ) / 28 (НИП) | D6: „[29, с. 44–45]“ при петте първи принципа на Merrill. | E6: „[29]“ — цитира се цялата статия. | F6: Няма достъп до пълния текст: копията в web.mit.edu, csapoer.pbworks.com и mdavidmerrill.wordpress.com са недостъпни. Съдържанието на твърдението е потвърдено от резюмето, но страничният локатор не е. | G6: [29] M. D. Merrill, First principles of instruction, ETR&D, т. 50, кн. 3, с. 43–59, 2002 | H6: Резюмето изброява петте принципа дословно: „Learning is promoted when learners are engaged in solving real-world problems… when existing knowledge is activated… when new knowledge is demonstrated… when new knowledge is applied… when new knowledge is integrated into the learner’s world.“ | I6: https://link.springer.com/article/10.1007/BF02505024 | J6: 31.08.2026
A7: 6 | B7: МТ + НИП | C7: 1.2, абз. 50 (МТ) / 29 (НИП) | D7: „…генериращият модел произвежда информативен текст без усилие, а учебен текст само по изключение.“ | E7: „…произвежда информативен текст без усилие, а учебен — само когато това е изрично изискано от него.“ | F7: „По изключение“ твърди емпирична рядкост, за която няма източник; действителното условие е наличието на изрично изискване в подсказа. | G7: — | H7: — | I7: — | J7: 31.08.2026
A8: 7 | B8: МТ + НИП | C8: 1.2, абз. 54 (МТ) / 33 (НИП) | D8: „…рамките за генериране въвеждат изрични ограничения върху броя на думите… именно защото зададеният обем не се спазва сам по себе си [47]“ — и след първата поправка [47] пак стоеше като подкрепа на твърдение за обем спрямо учебно време. | E8: Абзацът е пренаписан. Твърдението за обем/време е обозначено като методологическо решение на разработката; [47] подкрепя само описанието, че източниците разработват количествения контрол през равнището на езика. | F8: Източникът е за съобразяване с езиковото равнище (grade-appropriate readability), не за съотнасяне на обема с учебното време — възражение на автора, потвърдено при повторна проверка. | G8: [47] в МТ / [41] в НИП — Z. Liu и кол., COGENT, BEA 2025 | H8: „…control readability through length, vocabulary, and sentence complexity…“ — „length“ тук е дължина в служба на четивността, не обем спрямо занятие. | I8: https://aclanthology.org/2025.bea-1.10/ | J8: 31.08.2026
A9: 8 | B9: МТ + НИП | C9: 1.2, абз. 54 (МТ) / 33 (НИП) | D9: Целият абзац „Изискванията към структурата имат и количествено измерение…“ — след две поправки остана вътрешно противоречив: първата половина въвеждаше показател за обем спрямо учебно време, втората обясняваше, че литературата не го поддържа. | E9: Абзацът е премахнат изцяло. | F9: Решаващо: противоречи на собствения модел. Т. 3.3, абз. 221: „Преобразуването на обема в учебно време остава преценка на преподавателя, който познава курса, и затова не се вписва в модела като отделно изискване.“ Темата вече е покрита коректно в т. 2.3 (абз. 167) и от показател П14. | G9: — | H9: — | I9: — | J9: 31.08.2026
